{
  "generated_at": "2026-03-30T07:11:19",
  "summary_by_sector": [
    {
      "sector": "Oil & Gas E&P",
      "count_latest_day": 30,
      "change_vs_prev_day": 5,
      "percentage": 26.5
    },
    {
      "sector": "Oil & Gas Integrated",
      "count_latest_day": 13,
      "change_vs_prev_day": 3,
      "percentage": 11.5
    },
    {
      "sector": "Chemicals",
      "count_latest_day": 7,
      "change_vs_prev_day": 3,
      "percentage": 6.2
    },
    {
      "sector": "Oil & Gas Equipment & Services",
      "count_latest_day": 8,
      "change_vs_prev_day": 2,
      "percentage": 7.1
    },
    {
      "sector": "Thermal Coal",
      "count_latest_day": 3,
      "change_vs_prev_day": 2,
      "percentage": 2.7
    },
    {
      "sector": "Oil & Gas Midstream",
      "count_latest_day": 8,
      "change_vs_prev_day": 1,
      "percentage": 7.1
    },
    {
      "sector": "Oil & Gas Refining & Marketing",
      "count_latest_day": 7,
      "change_vs_prev_day": 1,
      "percentage": 6.2
    },
    {
      "sector": "Specialty Retail",
      "count_latest_day": 2,
      "change_vs_prev_day": 1,
      "percentage": 1.8
    },
    {
      "sector": "Food Distribution",
      "count_latest_day": 2,
      "change_vs_prev_day": 1,
      "percentage": 1.8
    },
    {
      "sector": "Farm Products",
      "count_latest_day": 1,
      "change_vs_prev_day": 1,
      "percentage": 0.9
    },
    {
      "sector": "Engineering & Construction",
      "count_latest_day": 1,
      "change_vs_prev_day": 1,
      "percentage": 0.9
    },
    {
      "sector": "Agricultural Inputs",
      "count_latest_day": 1,
      "change_vs_prev_day": 1,
      "percentage": 0.9
    },
    {
      "sector": "Utilities - Regulated Electric",
      "count_latest_day": 1,
      "change_vs_prev_day": 1,
      "percentage": 0.9
    },
    {
      "sector": "Publishing",
      "count_latest_day": 1,
      "change_vs_prev_day": 1,
      "percentage": 0.9
    },
    {
      "sector": "Utilities - Diversified",
      "count_latest_day": 1,
      "change_vs_prev_day": 1,
      "percentage": 0.9
    },
    {
      "sector": "Solar",
      "count_latest_day": 1,
      "change_vs_prev_day": 1,
      "percentage": 0.9
    },
    {
      "sector": "Rental & Leasing Services",
      "count_latest_day": 1,
      "change_vs_prev_day": 1,
      "percentage": 0.9
    },
    {
      "sector": "Packaged Foods",
      "count_latest_day": 3,
      "change_vs_prev_day": 0,
      "percentage": 2.7
    },
    {
      "sector": "Banks - Regional",
      "count_latest_day": 1,
      "change_vs_prev_day": 0,
      "percentage": 0.9
    },
    {
      "sector": "Telecom Services",
      "count_latest_day": 1,
      "change_vs_prev_day": 0,
      "percentage": 0.9
    },
    {
      "sector": "Aluminum",
      "count_latest_day": 0,
      "change_vs_prev_day": 0,
      "percentage": 0.0
    },
    {
      "sector": "Business Equipment & Supplies",
      "count_latest_day": 0,
      "change_vs_prev_day": 0,
      "percentage": 0.0
    },
    {
      "sector": "Medical Distribution",
      "count_latest_day": 0,
      "change_vs_prev_day": 0,
      "percentage": 0.0
    },
    {
      "sector": "Other Industrial Metals & Mining",
      "count_latest_day": 0,
      "change_vs_prev_day": 0,
      "percentage": 0.0
    },
    {
      "sector": "Electrical Equipment & Parts",
      "count_latest_day": 0,
      "change_vs_prev_day": 0,
      "percentage": 0.0
    },
    {
      "sector": "Semiconductor Equipment & Materials",
      "count_latest_day": 0,
      "change_vs_prev_day": 0,
      "percentage": 0.0
    },
    {
      "sector": "Specialty Industrial Machinery",
      "count_latest_day": 0,
      "change_vs_prev_day": 0,
      "percentage": 0.0
    },
    {
      "sector": "Medical Devices",
      "count_latest_day": 0,
      "change_vs_prev_day": 0,
      "percentage": 0.0
    },
    {
      "sector": "Beverages - Non-Alcoholic",
      "count_latest_day": 0,
      "change_vs_prev_day": 0,
      "percentage": 0.0
    },
    {
      "sector": "Lodging",
      "count_latest_day": 0,
      "change_vs_prev_day": 0,
      "percentage": 0.0
    },
    {
      "sector": "Consulting Services",
      "count_latest_day": 0,
      "change_vs_prev_day": 0,
      "percentage": 0.0
    },
    {
      "sector": "Restaurants",
      "count_latest_day": 0,
      "change_vs_prev_day": 0,
      "percentage": 0.0
    },
    {
      "sector": "Computer Hardware",
      "count_latest_day": 0,
      "change_vs_prev_day": 0,
      "percentage": 0.0
    },
    {
      "sector": "REIT - Retail",
      "count_latest_day": 0,
      "change_vs_prev_day": 0,
      "percentage": 0.0
    },
    {
      "sector": "Household & Personal Products",
      "count_latest_day": 0,
      "change_vs_prev_day": 0,
      "percentage": 0.0
    },
    {
      "sector": "Real Estate - Development",
      "count_latest_day": 0,
      "change_vs_prev_day": 0,
      "percentage": 0.0
    },
    {
      "sector": "Staffing & Employment Services",
      "count_latest_day": 0,
      "change_vs_prev_day": 0,
      "percentage": 0.0
    },
    {
      "sector": "Auto Parts",
      "count_latest_day": 0,
      "change_vs_prev_day": 0,
      "percentage": 0.0
    },
    {
      "sector": "REIT - Specialty",
      "count_latest_day": 0,
      "change_vs_prev_day": 0,
      "percentage": 0.0
    },
    {
      "sector": "Diagnostics & Research",
      "count_latest_day": 0,
      "change_vs_prev_day": 0,
      "percentage": 0.0
    },
    {
      "sector": "REIT - Industrial",
      "count_latest_day": 0,
      "change_vs_prev_day": 0,
      "percentage": 0.0
    },
    {
      "sector": "REIT - Healthcare Facilities",
      "count_latest_day": 0,
      "change_vs_prev_day": 0,
      "percentage": 0.0
    },
    {
      "sector": "Confectioners",
      "count_latest_day": 0,
      "change_vs_prev_day": 0,
      "percentage": 0.0
    },
    {
      "sector": "Grocery Stores",
      "count_latest_day": 0,
      "change_vs_prev_day": 0,
      "percentage": 0.0
    },
    {
      "sector": "Insurance - Life",
      "count_latest_day": 0,
      "change_vs_prev_day": 0,
      "percentage": 0.0
    },
    {
      "sector": "Metal Fabrication",
      "count_latest_day": 0,
      "change_vs_prev_day": 0,
      "percentage": 0.0
    },
    {
      "sector": "Health Information Services",
      "count_latest_day": 0,
      "change_vs_prev_day": 0,
      "percentage": 0.0
    },
    {
      "sector": "Scientific & Technical Instruments",
      "count_latest_day": 0,
      "change_vs_prev_day": 0,
      "percentage": 0.0
    },
    {
      "sector": "Electronic Components",
      "count_latest_day": 0,
      "change_vs_prev_day": 0,
      "percentage": 0.0
    },
    {
      "sector": "Insurance - Property & Casualty",
      "count_latest_day": 0,
      "change_vs_prev_day": 0,
      "percentage": 0.0
    },
    {
      "sector": "Residential Construction",
      "count_latest_day": 0,
      "change_vs_prev_day": 0,
      "percentage": 0.0
    },
    {
      "sector": "Furnishings",
      "count_latest_day": 0,
      "change_vs_prev_day": 0,
      "percentage": 0.0
    },
    {
      "sector": "Fixtures & Appliances",
      "count_latest_day": 0,
      "change_vs_prev_day": 0,
      "percentage": 0.0
    },
    {
      "sector": "Internet Content & Information",
      "count_latest_day": 0,
      "change_vs_prev_day": 0,
      "percentage": 0.0
    },
    {
      "sector": "Utilities - Independent Power Producers",
      "count_latest_day": 0,
      "change_vs_prev_day": 0,
      "percentage": 0.0
    },
    {
      "sector": "Footwear & Accessories",
      "count_latest_day": 0,
      "change_vs_prev_day": 0,
      "percentage": 0.0
    },
    {
      "sector": "Integrated Freight & Logistics",
      "count_latest_day": 0,
      "change_vs_prev_day": 0,
      "percentage": 0.0
    },
    {
      "sector": "Marine Shipping",
      "count_latest_day": 0,
      "change_vs_prev_day": 0,
      "percentage": 0.0
    },
    {
      "sector": "Advertising Agencies",
      "count_latest_day": 0,
      "change_vs_prev_day": 0,
      "percentage": 0.0
    },
    {
      "sector": "Other Precious Metals & Mining",
      "count_latest_day": 0,
      "change_vs_prev_day": 0,
      "percentage": 0.0
    },
    {
      "sector": "Utilities - Regulated Gas",
      "count_latest_day": 0,
      "change_vs_prev_day": 0,
      "percentage": 0.0
    },
    {
      "sector": "Utilities - Regulated Water",
      "count_latest_day": 0,
      "change_vs_prev_day": 0,
      "percentage": 0.0
    },
    {
      "sector": "Real Estate - Diversified",
      "count_latest_day": 0,
      "change_vs_prev_day": 0,
      "percentage": 0.0
    },
    {
      "sector": "Shell Companies",
      "count_latest_day": 11,
      "change_vs_prev_day": -1,
      "percentage": 9.7
    },
    {
      "sector": "Communication Equipment",
      "count_latest_day": 0,
      "change_vs_prev_day": -1,
      "percentage": 0.0
    },
    {
      "sector": "Software - Infrastructure",
      "count_latest_day": 0,
      "change_vs_prev_day": -1,
      "percentage": 0.0
    },
    {
      "sector": "Apparel Retail",
      "count_latest_day": 0,
      "change_vs_prev_day": -1,
      "percentage": 0.0
    },
    {
      "sector": "Asset Management",
      "count_latest_day": 0,
      "change_vs_prev_day": -1,
      "percentage": 0.0
    },
    {
      "sector": "Semiconductors",
      "count_latest_day": 0,
      "change_vs_prev_day": -1,
      "percentage": 0.0
    },
    {
      "sector": "Specialty Business Services",
      "count_latest_day": 0,
      "change_vs_prev_day": -1,
      "percentage": 0.0
    },
    {
      "sector": "Drug Manufacturers - Specialty & Generic",
      "count_latest_day": 0,
      "change_vs_prev_day": -1,
      "percentage": 0.0
    },
    {
      "sector": "REIT - Residential",
      "count_latest_day": 0,
      "change_vs_prev_day": -1,
      "percentage": 0.0
    },
    {
      "sector": "Insurance - Reinsurance",
      "count_latest_day": 0,
      "change_vs_prev_day": -1,
      "percentage": 0.0
    },
    {
      "sector": "Aerospace & Defense",
      "count_latest_day": 0,
      "change_vs_prev_day": -1,
      "percentage": 0.0
    },
    {
      "sector": "Education & Training Services",
      "count_latest_day": 0,
      "change_vs_prev_day": -1,
      "percentage": 0.0
    },
    {
      "sector": "Medical Care Facilities",
      "count_latest_day": 0,
      "change_vs_prev_day": -1,
      "percentage": 0.0
    },
    {
      "sector": "Luxury Goods",
      "count_latest_day": 0,
      "change_vs_prev_day": -1,
      "percentage": 0.0
    },
    {
      "sector": "REIT - Office",
      "count_latest_day": 0,
      "change_vs_prev_day": -1,
      "percentage": 0.0
    },
    {
      "sector": "Oil & Gas Drilling",
      "count_latest_day": 3,
      "change_vs_prev_day": -2,
      "percentage": 2.7
    },
    {
      "sector": "Software - Application",
      "count_latest_day": 1,
      "change_vs_prev_day": -2,
      "percentage": 0.9
    },
    {
      "sector": "Specialty Chemicals",
      "count_latest_day": 3,
      "change_vs_prev_day": -3,
      "percentage": 2.7
    },
    {
      "sector": "Biotechnology",
      "count_latest_day": 2,
      "change_vs_prev_day": -9,
      "percentage": 1.8
    }
  ],
  "highs_by_stock": [
    {
      "ticker": "BWXT",
      "industry": "Aerospace & Defense",
      "close": 202.59,
      "high_50d": 222.13,
      "high_52w": 222.13,
      "diff_pct": 0.0,
      "recent_high_dates": [
        "2026-03-25"
      ]
    },
    {
      "ticker": "PL",
      "industry": "Aerospace & Defense",
      "close": 30.86,
      "high_50d": 35.37,
      "high_52w": 35.37,
      "diff_pct": 0.0,
      "recent_high_dates": [
        "2026-03-25"
      ]
    },
    {
      "ticker": "RGR",
      "industry": "Aerospace & Defense",
      "close": 40.83,
      "high_50d": 43.53,
      "high_52w": 46.97,
      "diff_pct": 7.9,
      "recent_high_dates": [
        "2026-03-25"
      ]
    },
    {
      "ticker": "SATL",
      "industry": "Aerospace & Defense",
      "close": 5.93,
      "high_50d": 6.42,
      "high_52w": 6.42,
      "diff_pct": 0.0,
      "recent_high_dates": [
        "2026-03-25",
        "2026-03-26"
      ]
    },
    {
      "ticker": "SWBI",
      "industry": "Aerospace & Defense",
      "close": 14.66,
      "high_50d": 15.07,
      "high_52w": 15.07,
      "diff_pct": 0.0,
      "recent_high_dates": [
        "2026-03-25"
      ]
    },
    {
      "ticker": "CF",
      "industry": "Agricultural Inputs",
      "close": 136.45,
      "high_50d": 136.45,
      "high_52w": 136.45,
      "diff_pct": 0.0,
      "recent_high_dates": [
        "2026-03-27"
      ]
    },
    {
      "ticker": "BURL",
      "industry": "Apparel Retail",
      "close": 312.75,
      "high_50d": 329.27,
      "high_52w": 329.27,
      "diff_pct": 0.0,
      "recent_high_dates": [
        "2026-03-25"
      ]
    },
    {
      "ticker": "CURV",
      "industry": "Apparel Retail",
      "close": 1.79,
      "high_50d": 1.79,
      "high_52w": 6.46,
      "diff_pct": 260.9,
      "recent_high_dates": [
        "2026-03-27"
      ]
    },
    {
      "ticker": "ROST",
      "industry": "Apparel Retail",
      "close": 211.69,
      "high_50d": 216.03,
      "high_52w": 216.03,
      "diff_pct": 0.0,
      "recent_high_dates": [
        "2026-03-25"
      ]
    },
    {
      "ticker": "TLYS",
      "industry": "Apparel Retail",
      "close": 4.09,
      "high_50d": 4.2,
      "high_52w": 4.2,
      "diff_pct": 0.0,
      "recent_high_dates": [
        "2026-03-26"
      ]
    },
    {
      "ticker": "FHI",
      "industry": "Asset Management",
      "close": 56.0,
      "high_50d": 57.5,
      "high_52w": 57.5,
      "diff_pct": 0.0,
      "recent_high_dates": [
        "2026-03-25"
      ]
    },
    {
      "ticker": "INV",
      "industry": "Asset Management",
      "close": 3.8,
      "high_50d": 4.38,
      "high_52w": 8.15,
      "diff_pct": 86.1,
      "recent_high_dates": [
        "2026-03-25"
      ]
    },
    {
      "ticker": "RSF",
      "industry": "Asset Management",
      "close": 14.58,
      "high_50d": 15.07,
      "high_52w": 15.07,
      "diff_pct": 0.0,
      "recent_high_dates": [
        "2026-03-26"
      ]
    },
    {
      "ticker": "SSSS",
      "industry": "Asset Management",
      "close": 10.05,
      "high_50d": 10.55,
      "high_52w": 10.55,
      "diff_pct": 0.0,
      "recent_high_dates": [
        "2026-03-25"
      ]
    },
    {
      "ticker": "WHF",
      "industry": "Asset Management",
      "close": 7.14,
      "high_50d": 7.32,
      "high_52w": 8.37,
      "diff_pct": 14.3,
      "recent_high_dates": [
        "2026-03-25"
      ]
    },
    {
      "ticker": "CARG",
      "industry": "Auto & Truck Dealerships",
      "close": 35.01,
      "high_50d": 35.66,
      "high_52w": 39.03,
      "diff_pct": 9.5,
      "recent_high_dates": [
        "2026-03-26"
      ]
    },
    {
      "ticker": "SAH",
      "industry": "Auto & Truck Dealerships",
      "close": 65.93,
      "high_50d": 66.8,
      "high_52w": 87.27,
      "diff_pct": 30.6,
      "recent_high_dates": [
        "2026-03-26"
      ]
    },
    {
      "ticker": "CVGI",
      "industry": "Auto Parts",
      "close": 3.51,
      "high_50d": 3.77,
      "high_52w": 3.77,
      "diff_pct": 0.0,
      "recent_high_dates": [
        "2026-03-25"
      ]
    },
    {
      "ticker": "BCBP",
      "industry": "Banks - Regional",
      "close": 8.64,
      "high_50d": 8.77,
      "high_52w": 9.5,
      "diff_pct": 8.3,
      "recent_high_dates": [
        "2026-03-25",
        "2026-03-26"
      ]
    },
    {
      "ticker": "FCBC",
      "industry": "Banks - Regional",
      "close": 41.19,
      "high_50d": 41.19,
      "high_52w": 41.19,
      "diff_pct": 0.0,
      "recent_high_dates": [
        "2026-03-26",
        "2026-03-27"
      ]
    },
    {
      "ticker": "RVSB",
      "industry": "Banks - Regional",
      "close": 5.52,
      "high_50d": 5.53,
      "high_52w": 6.33,
      "diff_pct": 14.5,
      "recent_high_dates": [
        "2026-03-26"
      ]
    },
    {
      "ticker": "ADAG",
      "industry": "Biotechnology",
      "close": 3.77,
      "high_50d": 4.14,
      "high_52w": 4.14,
      "diff_pct": 0.0,
      "recent_high_dates": [
        "2026-03-26"
      ]
    },
    {
      "ticker": "CNTA",
      "industry": "Biotechnology",
      "close": 28.7,
      "high_50d": 29.4,
      "high_52w": 29.91,
      "diff_pct": 1.7,
      "recent_high_dates": [
        "2026-03-26"
      ]
    },
    {
      "ticker": "CNTB",
      "industry": "Biotechnology",
      "close": 3.45,
      "high_50d": 3.69,
      "high_52w": 3.69,
      "diff_pct": 0.0,
      "recent_high_dates": [
        "2026-03-25",
        "2026-03-26"
      ]
    },
    {
      "ticker": "ELVN",
      "industry": "Biotechnology",
      "close": 38.83,
      "high_50d": 39.29,
      "high_52w": 39.29,
      "diff_pct": 0.0,
      "recent_high_dates": [
        "2026-03-25",
        "2026-03-26"
      ]
    },
    {
      "ticker": "ENLV",
      "industry": "Biotechnology",
      "close": 1.05,
      "high_50d": 1.2,
      "high_52w": 1.82,
      "diff_pct": 51.7,
      "recent_high_dates": [
        "2026-03-25"
      ]
    },
    {
      "ticker": "ERAS",
      "industry": "Biotechnology",
      "close": 14.97,
      "high_50d": 15.99,
      "high_52w": 15.99,
      "diff_pct": 0.0,
      "recent_high_dates": [
        "2026-03-25"
      ]
    },
    {
      "ticker": "EWTX",
      "industry": "Biotechnology",
      "close": 30.84,
      "high_50d": 31.94,
      "high_52w": 31.94,
      "diff_pct": 0.0,
      "recent_high_dates": [
        "2026-03-25"
      ]
    },
    {
      "ticker": "FDMT",
      "industry": "Biotechnology",
      "close": 9.33,
      "high_50d": 10.18,
      "high_52w": 12.27,
      "diff_pct": 20.5,
      "recent_high_dates": [
        "2026-03-26"
      ]
    },
    {
      "ticker": "FOLD",
      "industry": "Biotechnology",
      "close": 14.41,
      "high_50d": 14.43,
      "high_52w": 14.43,
      "diff_pct": 0.0,
      "recent_high_dates": [
        "2026-03-25",
        "2026-03-26"
      ]
    },
    {
      "ticker": "GRCE",
      "industry": "Biotechnology",
      "close": 4.67,
      "high_50d": 4.77,
      "high_52w": 4.77,
      "diff_pct": 0.0,
      "recent_high_dates": [
        "2026-03-25",
        "2026-03-26"
      ]
    },
    {
      "ticker": "KALV",
      "industry": "Biotechnology",
      "close": 19.33,
      "high_50d": 19.33,
      "high_52w": 19.33,
      "diff_pct": 0.0,
      "recent_high_dates": [
        "2026-03-26",
        "2026-03-27"
      ]
    },
    {
      "ticker": "KOD",
      "industry": "Biotechnology",
      "close": 37.0,
      "high_50d": 39.76,
      "high_52w": 39.76,
      "diff_pct": 0.0,
      "recent_high_dates": [
        "2026-03-26"
      ]
    },
    {
      "ticker": "MDGL",
      "industry": "Biotechnology",
      "close": 510.68,
      "high_50d": 518.76,
      "high_52w": 602.83,
      "diff_pct": 16.2,
      "recent_high_dates": [
        "2026-03-26"
      ]
    },
    {
      "ticker": "NRXP",
      "industry": "Biotechnology",
      "close": 2.19,
      "high_50d": 2.41,
      "high_52w": 3.67,
      "diff_pct": 52.3,
      "recent_high_dates": [
        "2026-03-25"
      ]
    },
    {
      "ticker": "OKUR",
      "industry": "Biotechnology",
      "close": 3.99,
      "high_50d": 4.59,
      "high_52w": 4.69,
      "diff_pct": 2.2,
      "recent_high_dates": [
        "2026-03-26"
      ]
    },
    {
      "ticker": "ORKA",
      "industry": "Biotechnology",
      "close": 44.48,
      "high_50d": 45.46,
      "high_52w": 45.46,
      "diff_pct": 0.0,
      "recent_high_dates": [
        "2026-03-25",
        "2026-03-26"
      ]
    },
    {
      "ticker": "PTGX",
      "industry": "Biotechnology",
      "close": 98.97,
      "high_50d": 104.31,
      "high_52w": 104.31,
      "diff_pct": 0.0,
      "recent_high_dates": [
        "2026-03-25"
      ]
    },
    {
      "ticker": "SMMT",
      "industry": "Biotechnology",
      "close": 16.58,
      "high_50d": 17.94,
      "high_52w": 36.7,
      "diff_pct": 104.6,
      "recent_high_dates": [
        "2026-03-25"
      ]
    },
    {
      "ticker": "SNDX",
      "industry": "Biotechnology",
      "close": 23.49,
      "high_50d": 24.7,
      "high_52w": 24.7,
      "diff_pct": 0.0,
      "recent_high_dates": [
        "2026-03-26"
      ]
    },
    {
      "ticker": "SRPT",
      "industry": "Biotechnology",
      "close": 19.97,
      "high_50d": 23.77,
      "high_52w": 71.81,
      "diff_pct": 202.1,
      "recent_high_dates": [
        "2026-03-25"
      ]
    },
    {
      "ticker": "SRZN",
      "industry": "Biotechnology",
      "close": 28.9,
      "high_50d": 28.9,
      "high_52w": 28.9,
      "diff_pct": 0.0,
      "recent_high_dates": [
        "2026-03-27"
      ]
    },
    {
      "ticker": "STTK",
      "industry": "Biotechnology",
      "close": 6.02,
      "high_50d": 6.37,
      "high_52w": 6.37,
      "diff_pct": 0.0,
      "recent_high_dates": [
        "2026-03-25"
      ]
    },
    {
      "ticker": "SYRE",
      "industry": "Biotechnology",
      "close": 47.31,
      "high_50d": 47.52,
      "high_52w": 47.52,
      "diff_pct": 0.0,
      "recent_high_dates": [
        "2026-03-25",
        "2026-03-26"
      ]
    },
    {
      "ticker": "TERN",
      "industry": "Biotechnology",
      "close": 52.92,
      "high_50d": 53.17,
      "high_52w": 53.17,
      "diff_pct": 0.0,
      "recent_high_dates": [
        "2026-03-25",
        "2026-03-26"
      ]
    },
    {
      "ticker": "TGTX",
      "industry": "Biotechnology",
      "close": 31.75,
      "high_50d": 31.98,
      "high_52w": 45.51,
      "diff_pct": 42.3,
      "recent_high_dates": [
        "2026-03-25",
        "2026-03-26"
      ]
    },
    {
      "ticker": "TLX",
      "industry": "Biotechnology",
      "close": 9.2,
      "high_50d": 9.2,
      "high_52w": 19.22,
      "diff_pct": 108.9,
      "recent_high_dates": [
        "2026-03-27"
      ]
    },
    {
      "ticker": "TNGX",
      "industry": "Biotechnology",
      "close": 19.26,
      "high_50d": 20.88,
      "high_52w": 20.88,
      "diff_pct": 0.0,
      "recent_high_dates": [
        "2026-03-25"
      ]
    },
    {
      "ticker": "XOMA",
      "industry": "Biotechnology",
      "close": 30.17,
      "high_50d": 30.53,
      "high_52w": 39.72,
      "diff_pct": 30.1,
      "recent_high_dates": [
        "2026-03-25",
        "2026-03-26"
      ]
    },
    {
      "ticker": "INVE",
      "industry": "Building Products & Equipment",
      "close": 3.67,
      "high_50d": 3.93,
      "high_52w": 4.01,
      "diff_pct": 2.0,
      "recent_high_dates": [
        "2026-03-25"
      ]
    },
    {
      "ticker": "ACTG",
      "industry": "Business Equipment & Supplies",
      "close": 4.84,
      "high_50d": 5.04,
      "high_52w": 5.04,
      "diff_pct": 0.0,
      "recent_high_dates": [
        "2026-03-25"
      ]
    },
    {
      "ticker": "VIRT",
      "industry": "Capital Markets",
      "close": 42.52,
      "high_50d": 43.74,
      "high_52w": 44.31,
      "diff_pct": 1.3,
      "recent_high_dates": [
        "2026-03-25"
      ]
    },
    {
      "ticker": "ASIX",
      "industry": "Chemicals",
      "close": 24.06,
      "high_50d": 24.43,
      "high_52w": 24.59,
      "diff_pct": 0.7,
      "recent_high_dates": [
        "2026-03-25",
        "2026-03-26"
      ]
    },
    {
      "ticker": "CE",
      "industry": "Chemicals",
      "close": 63.41,
      "high_50d": 63.41,
      "high_52w": 63.41,
      "diff_pct": 0.0,
      "recent_high_dates": [
        "2026-03-25",
        "2026-03-27"
      ]
    },
    {
      "ticker": "DOW",
      "industry": "Chemicals",
      "close": 40.82,
      "high_50d": 40.82,
      "high_52w": 40.82,
      "diff_pct": 0.0,
      "recent_high_dates": [
        "2026-03-25",
        "2026-03-27"
      ]
    },
    {
      "ticker": "GPRE",
      "industry": "Chemicals",
      "close": 16.89,
      "high_50d": 16.89,
      "high_52w": 16.89,
      "diff_pct": 0.0,
      "recent_high_dates": [
        "2026-03-27"
      ]
    },
    {
      "ticker": "MEOH",
      "industry": "Chemicals",
      "close": 65.22,
      "high_50d": 65.22,
      "high_52w": 65.22,
      "diff_pct": 0.0,
      "recent_high_dates": [
        "2026-03-26",
        "2026-03-27"
      ]
    },
    {
      "ticker": "OLN",
      "industry": "Chemicals",
      "close": 29.01,
      "high_50d": 29.01,
      "high_52w": 29.01,
      "diff_pct": 0.0,
      "recent_high_dates": [
        "2026-03-25",
        "2026-03-26",
        "2026-03-27"
      ]
    },
    {
      "ticker": "REX",
      "industry": "Chemicals",
      "close": 47.73,
      "high_50d": 47.73,
      "high_52w": 47.73,
      "diff_pct": 0.0,
      "recent_high_dates": [
        "2026-03-25",
        "2026-03-26",
        "2026-03-27"
      ]
    },
    {
      "ticker": "TROX",
      "industry": "Chemicals",
      "close": 9.12,
      "high_50d": 9.12,
      "high_52w": 9.12,
      "diff_pct": 0.0,
      "recent_high_dates": [
        "2026-03-25",
        "2026-03-26",
        "2026-03-27"
      ]
    },
    {
      "ticker": "ADTN",
      "industry": "Communication Equipment",
      "close": 12.93,
      "high_50d": 12.97,
      "high_52w": 12.97,
      "diff_pct": 0.0,
      "recent_high_dates": [
        "2026-03-25",
        "2026-03-26"
      ]
    },
    {
      "ticker": "AUDC",
      "industry": "Communication Equipment",
      "close": 8.33,
      "high_50d": 8.67,
      "high_52w": 10.32,
      "diff_pct": 19.0,
      "recent_high_dates": [
        "2026-03-25"
      ]
    },
    {
      "ticker": "HPE",
      "industry": "Communication Equipment",
      "close": 23.94,
      "high_50d": 25.78,
      "high_52w": 25.93,
      "diff_pct": 0.6,
      "recent_high_dates": [
        "2026-03-25"
      ]
    },
    {
      "ticker": "OCC",
      "industry": "Communication Equipment",
      "close": 9.14,
      "high_50d": 10.12,
      "high_52w": 10.69,
      "diff_pct": 5.6,
      "recent_high_dates": [
        "2026-03-25"
      ]
    },
    {
      "ticker": "SILC",
      "industry": "Communication Equipment",
      "close": 20.79,
      "high_50d": 22.6,
      "high_52w": 22.6,
      "diff_pct": 0.0,
      "recent_high_dates": [
        "2026-03-25"
      ]
    },
    {
      "ticker": "UI",
      "industry": "Communication Equipment",
      "close": 779.92,
      "high_50d": 839.05,
      "high_52w": 839.05,
      "diff_pct": 0.0,
      "recent_high_dates": [
        "2026-03-25"
      ]
    },
    {
      "ticker": "VIAV",
      "industry": "Communication Equipment",
      "close": 34.64,
      "high_50d": 37.27,
      "high_52w": 37.27,
      "diff_pct": 0.0,
      "recent_high_dates": [
        "2026-03-25"
      ]
    },
    {
      "ticker": "DELL",
      "industry": "Computer Hardware",
      "close": 171.81,
      "high_50d": 184.01,
      "high_52w": 184.01,
      "diff_pct": 0.0,
      "recent_high_dates": [
        "2026-03-25"
      ]
    },
    {
      "ticker": "FBYD",
      "industry": "Conglomerates",
      "close": 9.63,
      "high_50d": 9.63,
      "high_52w": 20.8,
      "diff_pct": 116.0,
      "recent_high_dates": [
        "2026-03-26",
        "2026-03-27"
      ]
    },
    {
      "ticker": "TUSK",
      "industry": "Conglomerates",
      "close": 2.85,
      "high_50d": 2.85,
      "high_52w": 3.01,
      "diff_pct": 5.6,
      "recent_high_dates": [
        "2026-03-26",
        "2026-03-27"
      ]
    },
    {
      "ticker": "ROMA",
      "industry": "Consulting Services",
      "close": 6.3,
      "high_50d": 10.34,
      "high_52w": 10.34,
      "diff_pct": 0.0,
      "recent_high_dates": [
        "2026-03-25"
      ]
    },
    {
      "ticker": "ASRT",
      "industry": "Drug Manufacturers - Specialty & Generic",
      "close": 19.39,
      "high_50d": 19.53,
      "high_52w": 19.53,
      "diff_pct": 0.0,
      "recent_high_dates": [
        "2026-03-25",
        "2026-03-26"
      ]
    },
    {
      "ticker": "CRDL",
      "industry": "Drug Manufacturers - Specialty & Generic",
      "close": 1.25,
      "high_50d": 1.25,
      "high_52w": 1.54,
      "diff_pct": 23.2,
      "recent_high_dates": [
        "2026-03-26",
        "2026-03-27"
      ]
    },
    {
      "ticker": "ETON",
      "industry": "Drug Manufacturers - Specialty & Generic",
      "close": 23.24,
      "high_50d": 23.84,
      "high_52w": 23.84,
      "diff_pct": 0.0,
      "recent_high_dates": [
        "2026-03-25"
      ]
    },
    {
      "ticker": "PAHC",
      "industry": "Drug Manufacturers - Specialty & Generic",
      "close": 53.88,
      "high_50d": 57.01,
      "high_52w": 57.01,
      "diff_pct": 0.0,
      "recent_high_dates": [
        "2026-03-25"
      ]
    },
    {
      "ticker": "AFYA",
      "industry": "Education & Training Services",
      "close": 14.75,
      "high_50d": 15.16,
      "high_52w": 18.78,
      "diff_pct": 23.9,
      "recent_high_dates": [
        "2026-03-25"
      ]
    },
    {
      "ticker": "APEI",
      "industry": "Education & Training Services",
      "close": 57.24,
      "high_50d": 58.54,
      "high_52w": 58.54,
      "diff_pct": 0.0,
      "recent_high_dates": [
        "2026-03-25"
      ]
    },
    {
      "ticker": "LINC",
      "industry": "Education & Training Services",
      "close": 40.91,
      "high_50d": 41.61,
      "high_52w": 41.61,
      "diff_pct": 0.0,
      "recent_high_dates": [
        "2026-03-25"
      ]
    },
    {
      "ticker": "LRN",
      "industry": "Education & Training Services",
      "close": 85.61,
      "high_50d": 88.6,
      "high_52w": 169.81,
      "diff_pct": 91.7,
      "recent_high_dates": [
        "2026-03-25"
      ]
    },
    {
      "ticker": "PRDO",
      "industry": "Education & Training Services",
      "close": 37.23,
      "high_50d": 37.89,
      "high_52w": 37.89,
      "diff_pct": 0.0,
      "recent_high_dates": [
        "2026-03-25",
        "2026-03-26"
      ]
    },
    {
      "ticker": "UTI",
      "industry": "Education & Training Services",
      "close": 37.19,
      "high_50d": 39.66,
      "high_52w": 39.66,
      "diff_pct": 0.0,
      "recent_high_dates": [
        "2026-03-25"
      ]
    },
    {
      "ticker": "NVT",
      "industry": "Electrical Equipment & Parts",
      "close": 116.98,
      "high_50d": 127.01,
      "high_52w": 127.01,
      "diff_pct": 0.0,
      "recent_high_dates": [
        "2026-03-25"
      ]
    },
    {
      "ticker": "VRT",
      "industry": "Electrical Equipment & Parts",
      "close": 251.07,
      "high_50d": 276.16,
      "high_52w": 276.16,
      "diff_pct": 0.0,
      "recent_high_dates": [
        "2026-03-25"
      ]
    },
    {
      "ticker": "FLEX",
      "industry": "Electronic Components",
      "close": 64.8,
      "high_50d": 70.02,
      "high_52w": 72.08,
      "diff_pct": 2.9,
      "recent_high_dates": [
        "2026-03-25"
      ]
    },
    {
      "ticker": "JBL",
      "industry": "Electronic Components",
      "close": 261.1,
      "high_50d": 283.24,
      "high_52w": 283.24,
      "diff_pct": 0.0,
      "recent_high_dates": [
        "2026-03-25"
      ]
    },
    {
      "ticker": "MPTI",
      "industry": "Electronic Components",
      "close": 69.03,
      "high_50d": 77.06,
      "high_52w": 77.06,
      "diff_pct": 0.0,
      "recent_high_dates": [
        "2026-03-25"
      ]
    },
    {
      "ticker": "PLXS",
      "industry": "Electronic Components",
      "close": 199.17,
      "high_50d": 217.26,
      "high_52w": 217.26,
      "diff_pct": 0.0,
      "recent_high_dates": [
        "2026-03-25"
      ]
    },
    {
      "ticker": "AGX",
      "industry": "Engineering & Construction",
      "close": 566.62,
      "high_50d": 566.62,
      "high_52w": 566.62,
      "diff_pct": 0.0,
      "recent_high_dates": [
        "2026-03-27"
      ]
    },
    {
      "ticker": "FIX",
      "industry": "Engineering & Construction",
      "close": 1366.77,
      "high_50d": 1470.64,
      "high_52w": 1470.64,
      "diff_pct": 0.0,
      "recent_high_dates": [
        "2026-03-25"
      ]
    },
    {
      "ticker": "GLDD",
      "industry": "Engineering & Construction",
      "close": 16.97,
      "high_50d": 16.98,
      "high_52w": 16.98,
      "diff_pct": 0.0,
      "recent_high_dates": [
        "2026-03-25"
      ]
    },
    {
      "ticker": "MTZ",
      "industry": "Engineering & Construction",
      "close": 316.01,
      "high_50d": 323.55,
      "high_52w": 323.55,
      "diff_pct": 0.0,
      "recent_high_dates": [
        "2026-03-25"
      ]
    },
    {
      "ticker": "MYRG",
      "industry": "Engineering & Construction",
      "close": 273.47,
      "high_50d": 285.18,
      "high_52w": 285.18,
      "diff_pct": 0.0,
      "recent_high_dates": [
        "2026-03-25"
      ]
    },
    {
      "ticker": "SIRI",
      "industry": "Entertainment",
      "close": 22.84,
      "high_50d": 22.99,
      "high_52w": 23.82,
      "diff_pct": 3.6,
      "recent_high_dates": [
        "2026-03-25"
      ]
    },
    {
      "ticker": "AGRO",
      "industry": "Farm Products",
      "close": 14.05,
      "high_50d": 14.7,
      "high_52w": 14.7,
      "diff_pct": 0.0,
      "recent_high_dates": [
        "2026-03-25"
      ]
    },
    {
      "ticker": "BG",
      "industry": "Farm Products",
      "close": 128.72,
      "high_50d": 128.72,
      "high_52w": 128.72,
      "diff_pct": 0.0,
      "recent_high_dates": [
        "2026-03-27"
      ]
    },
    {
      "ticker": "FRHC",
      "industry": "Financial Conglomerates",
      "close": 141.19,
      "high_50d": 145.84,
      "high_52w": 190.14,
      "diff_pct": 30.4,
      "recent_high_dates": [
        "2026-03-25"
      ]
    },
    {
      "ticker": "MKTW",
      "industry": "Financial Data & Stock Exchanges",
      "close": 19.13,
      "high_50d": 19.13,
      "high_52w": 19.59,
      "diff_pct": 2.4,
      "recent_high_dates": [
        "2026-03-25",
        "2026-03-26",
        "2026-03-27"
      ]
    },
    {
      "ticker": "XWIN",
      "industry": "Fixtures & Appliances",
      "close": 7.16,
      "high_50d": 7.25,
      "high_52w": 7.25,
      "diff_pct": 0.0,
      "recent_high_dates": [
        "2026-03-25"
      ]
    },
    {
      "ticker": "ANDE",
      "industry": "Food Distribution",
      "close": 73.19,
      "high_50d": 73.19,
      "high_52w": 73.19,
      "diff_pct": 0.0,
      "recent_high_dates": [
        "2026-03-25",
        "2026-03-27"
      ]
    },
    {
      "ticker": "UNFI",
      "industry": "Food Distribution",
      "close": 45.93,
      "high_50d": 45.93,
      "high_52w": 45.93,
      "diff_pct": 0.0,
      "recent_high_dates": [
        "2026-03-25",
        "2026-03-26",
        "2026-03-27"
      ]
    },
    {
      "ticker": "XWIN",
      "industry": "Furnishings",
      "close": 7.16,
      "high_50d": 7.25,
      "high_52w": 7.25,
      "diff_pct": 0.0,
      "recent_high_dates": [
        "2026-03-25"
      ]
    },
    {
      "ticker": "CDRO",
      "industry": "Gambling",
      "close": 8.28,
      "high_50d": 8.57,
      "high_52w": 8.7,
      "diff_pct": 1.5,
      "recent_high_dates": [
        "2026-03-25"
      ]
    },
    {
      "ticker": "BTSG",
      "industry": "Health Information Services",
      "close": 42.33,
      "high_50d": 44.82,
      "high_52w": 44.82,
      "diff_pct": 0.0,
      "recent_high_dates": [
        "2026-03-25"
      ]
    },
    {
      "ticker": "CCLD",
      "industry": "Health Information Services",
      "close": 3.49,
      "high_50d": 3.81,
      "high_52w": 3.84,
      "diff_pct": 0.8,
      "recent_high_dates": [
        "2026-03-25",
        "2026-03-26"
      ]
    },
    {
      "ticker": "EWCZ",
      "industry": "Household & Personal Products",
      "close": 5.78,
      "high_50d": 5.78,
      "high_52w": 6.36,
      "diff_pct": 10.0,
      "recent_high_dates": [
        "2026-03-25",
        "2026-03-26",
        "2026-03-27"
      ]
    },
    {
      "ticker": "HNST",
      "industry": "Household & Personal Products",
      "close": 2.88,
      "high_50d": 2.93,
      "high_52w": 5.51,
      "diff_pct": 88.1,
      "recent_high_dates": [
        "2026-03-25"
      ]
    },
    {
      "ticker": "LZMH",
      "industry": "Information Technology Services",
      "close": 1.55,
      "high_50d": 1.55,
      "high_52w": 28.68,
      "diff_pct": 1750.3,
      "recent_high_dates": [
        "2026-03-26",
        "2026-03-27"
      ]
    },
    {
      "ticker": "TSSI",
      "industry": "Information Technology Services",
      "close": 11.7,
      "high_50d": 13.34,
      "high_52w": 31.1,
      "diff_pct": 133.1,
      "recent_high_dates": [
        "2026-03-25"
      ]
    },
    {
      "ticker": "PRA",
      "industry": "Insurance - Property & Casualty",
      "close": 24.58,
      "high_50d": 24.75,
      "high_52w": 24.75,
      "diff_pct": 0.0,
      "recent_high_dates": [
        "2026-03-25"
      ]
    },
    {
      "ticker": "GLRE",
      "industry": "Insurance - Reinsurance",
      "close": 16.76,
      "high_50d": 17.12,
      "high_52w": 17.12,
      "diff_pct": 0.0,
      "recent_high_dates": [
        "2026-03-25",
        "2026-03-26"
      ]
    },
    {
      "ticker": "PERI",
      "industry": "Internet Content & Information",
      "close": 9.82,
      "high_50d": 10.28,
      "high_52w": 11.43,
      "diff_pct": 11.2,
      "recent_high_dates": [
        "2026-03-25",
        "2026-03-26"
      ]
    },
    {
      "ticker": "SOGP",
      "industry": "Internet Content & Information",
      "close": 16.69,
      "high_50d": 16.69,
      "high_52w": 32.5,
      "diff_pct": 94.7,
      "recent_high_dates": [
        "2026-03-25",
        "2026-03-27"
      ]
    },
    {
      "ticker": "TRON",
      "industry": "Leisure",
      "close": 2.17,
      "high_50d": 2.63,
      "high_52w": 11.04,
      "diff_pct": 319.8,
      "recent_high_dates": [
        "2026-03-25"
      ]
    },
    {
      "ticker": "ELA",
      "industry": "Luxury Goods",
      "close": 16.96,
      "high_50d": 17.45,
      "high_52w": 17.45,
      "diff_pct": 0.0,
      "recent_high_dates": [
        "2026-03-25",
        "2026-03-26"
      ]
    },
    {
      "ticker": "AIRS",
      "industry": "Medical Care Facilities",
      "close": 2.87,
      "high_50d": 3.25,
      "high_52w": 11.65,
      "diff_pct": 258.5,
      "recent_high_dates": [
        "2026-03-26"
      ]
    },
    {
      "ticker": "AUNA",
      "industry": "Medical Care Facilities",
      "close": 5.65,
      "high_50d": 5.98,
      "high_52w": 7.32,
      "diff_pct": 22.4,
      "recent_high_dates": [
        "2026-03-25"
      ]
    },
    {
      "ticker": "DVA",
      "industry": "Medical Care Facilities",
      "close": 154.43,
      "high_50d": 156.76,
      "high_52w": 156.76,
      "diff_pct": 0.0,
      "recent_high_dates": [
        "2026-03-26"
      ]
    },
    {
      "ticker": "EHAB",
      "industry": "Medical Care Facilities",
      "close": 13.66,
      "high_50d": 13.67,
      "high_52w": 13.67,
      "diff_pct": 0.0,
      "recent_high_dates": [
        "2026-03-25"
      ]
    },
    {
      "ticker": "BVS",
      "industry": "Medical Devices",
      "close": 8.94,
      "high_50d": 9.26,
      "high_52w": 9.51,
      "diff_pct": 2.7,
      "recent_high_dates": [
        "2026-03-25",
        "2026-03-26"
      ]
    },
    {
      "ticker": "CVRX",
      "industry": "Medical Devices",
      "close": 8.91,
      "high_50d": 9.38,
      "high_52w": 12.98,
      "diff_pct": 38.4,
      "recent_high_dates": [
        "2026-03-25"
      ]
    },
    {
      "ticker": "NBR",
      "industry": "Oil & Gas Drilling",
      "close": 89.6,
      "high_50d": 89.6,
      "high_52w": 89.6,
      "diff_pct": 0.0,
      "recent_high_dates": [
        "2026-03-25",
        "2026-03-26",
        "2026-03-27"
      ]
    },
    {
      "ticker": "NE",
      "industry": "Oil & Gas Drilling",
      "close": 49.81,
      "high_50d": 49.83,
      "high_52w": 49.83,
      "diff_pct": 0.0,
      "recent_high_dates": [
        "2026-03-26"
      ]
    },
    {
      "ticker": "PDS",
      "industry": "Oil & Gas Drilling",
      "close": 100.81,
      "high_50d": 101.96,
      "high_52w": 101.96,
      "diff_pct": 0.0,
      "recent_high_dates": [
        "2026-03-25"
      ]
    },
    {
      "ticker": "PTEN",
      "industry": "Oil & Gas Drilling",
      "close": 11.36,
      "high_50d": 11.36,
      "high_52w": 11.36,
      "diff_pct": 0.0,
      "recent_high_dates": [
        "2026-03-25",
        "2026-03-26",
        "2026-03-27"
      ]
    },
    {
      "ticker": "RIG",
      "industry": "Oil & Gas Drilling",
      "close": 6.93,
      "high_50d": 6.93,
      "high_52w": 6.93,
      "diff_pct": 0.0,
      "recent_high_dates": [
        "2026-03-25",
        "2026-03-26",
        "2026-03-27"
      ]
    },
    {
      "ticker": "SDRL",
      "industry": "Oil & Gas Drilling",
      "close": 45.41,
      "high_50d": 45.46,
      "high_52w": 45.46,
      "diff_pct": 0.0,
      "recent_high_dates": [
        "2026-03-26"
      ]
    },
    {
      "ticker": "SOC",
      "industry": "Oil & Gas Drilling",
      "close": 18.45,
      "high_50d": 18.45,
      "high_52w": 33.02,
      "diff_pct": 79.0,
      "recent_high_dates": [
        "2026-03-25",
        "2026-03-26",
        "2026-03-27"
      ]
    },
    {
      "ticker": "AMPY",
      "industry": "Oil & Gas E&P",
      "close": 6.56,
      "high_50d": 6.63,
      "high_52w": 6.63,
      "diff_pct": 0.0,
      "recent_high_dates": [
        "2026-03-26"
      ]
    },
    {
      "ticker": "APA",
      "industry": "Oil & Gas E&P",
      "close": 44.39,
      "high_50d": 44.39,
      "high_52w": 44.39,
      "diff_pct": 0.0,
      "recent_high_dates": [
        "2026-03-25",
        "2026-03-26",
        "2026-03-27"
      ]
    },
    {
      "ticker": "AR",
      "industry": "Oil & Gas E&P",
      "close": 45.15,
      "high_50d": 45.15,
      "high_52w": 45.15,
      "diff_pct": 0.0,
      "recent_high_dates": [
        "2026-03-25",
        "2026-03-27"
      ]
    },
    {
      "ticker": "BTE",
      "industry": "Oil & Gas E&P",
      "close": 4.33,
      "high_50d": 4.33,
      "high_52w": 4.33,
      "diff_pct": 0.0,
      "recent_high_dates": [
        "2026-03-25",
        "2026-03-26",
        "2026-03-27"
      ]
    },
    {
      "ticker": "CHRD",
      "industry": "Oil & Gas E&P",
      "close": 145.35,
      "high_50d": 145.35,
      "high_52w": 145.35,
      "diff_pct": 0.0,
      "recent_high_dates": [
        "2026-03-25",
        "2026-03-26",
        "2026-03-27"
      ]
    },
    {
      "ticker": "COP",
      "industry": "Oil & Gas E&P",
      "close": 133.8,
      "high_50d": 133.8,
      "high_52w": 133.8,
      "diff_pct": 0.0,
      "recent_high_dates": [
        "2026-03-26",
        "2026-03-27"
      ]
    },
    {
      "ticker": "CRC",
      "industry": "Oil & Gas E&P",
      "close": 68.87,
      "high_50d": 68.87,
      "high_52w": 68.87,
      "diff_pct": 0.0,
      "recent_high_dates": [
        "2026-03-25",
        "2026-03-26",
        "2026-03-27"
      ]
    },
    {
      "ticker": "CRGY",
      "industry": "Oil & Gas E&P",
      "close": 13.7,
      "high_50d": 13.7,
      "high_52w": 13.7,
      "diff_pct": 0.0,
      "recent_high_dates": [
        "2026-03-25",
        "2026-03-26",
        "2026-03-27"
      ]
    },
    {
      "ticker": "CRT",
      "industry": "Oil & Gas E&P",
      "close": 10.63,
      "high_50d": 10.63,
      "high_52w": 12.38,
      "diff_pct": 16.5,
      "recent_high_dates": [
        "2026-03-25",
        "2026-03-26",
        "2026-03-27"
      ]
    },
    {
      "ticker": "CTRA",
      "industry": "Oil & Gas E&P",
      "close": 36.31,
      "high_50d": 36.31,
      "high_52w": 36.31,
      "diff_pct": 0.0,
      "recent_high_dates": [
        "2026-03-25",
        "2026-03-26",
        "2026-03-27"
      ]
    },
    {
      "ticker": "DMLP",
      "industry": "Oil & Gas E&P",
      "close": 28.05,
      "high_50d": 28.05,
      "high_52w": 28.05,
      "diff_pct": 0.0,
      "recent_high_dates": [
        "2026-03-26",
        "2026-03-27"
      ]
    },
    {
      "ticker": "DVN",
      "industry": "Oil & Gas E&P",
      "close": 52.07,
      "high_50d": 52.07,
      "high_52w": 52.07,
      "diff_pct": 0.0,
      "recent_high_dates": [
        "2026-03-25",
        "2026-03-26",
        "2026-03-27"
      ]
    },
    {
      "ticker": "EGY",
      "industry": "Oil & Gas E&P",
      "close": 6.44,
      "high_50d": 6.44,
      "high_52w": 6.44,
      "diff_pct": 0.0,
      "recent_high_dates": [
        "2026-03-26",
        "2026-03-27"
      ]
    },
    {
      "ticker": "EOG",
      "industry": "Oil & Gas E&P",
      "close": 149.56,
      "high_50d": 149.56,
      "high_52w": 149.56,
      "diff_pct": 0.0,
      "recent_high_dates": [
        "2026-03-25",
        "2026-03-26",
        "2026-03-27"
      ]
    },
    {
      "ticker": "EPM",
      "industry": "Oil & Gas E&P",
      "close": 4.66,
      "high_50d": 4.66,
      "high_52w": 5.08,
      "diff_pct": 9.0,
      "recent_high_dates": [
        "2026-03-27"
      ]
    },
    {
      "ticker": "EPSN",
      "industry": "Oil & Gas E&P",
      "close": 6.25,
      "high_50d": 6.25,
      "high_52w": 8.1,
      "diff_pct": 29.6,
      "recent_high_dates": [
        "2026-03-25",
        "2026-03-27"
      ]
    },
    {
      "ticker": "EQT",
      "industry": "Oil & Gas E&P",
      "close": 67.55,
      "high_50d": 67.93,
      "high_52w": 67.93,
      "diff_pct": 0.0,
      "recent_high_dates": [
        "2026-03-25"
      ]
    },
    {
      "ticker": "EXE",
      "industry": "Oil & Gas E&P",
      "close": 113.5,
      "high_50d": 113.92,
      "high_52w": 122.22,
      "diff_pct": 7.3,
      "recent_high_dates": [
        "2026-03-25"
      ]
    },
    {
      "ticker": "FANG",
      "industry": "Oil & Gas E&P",
      "close": 201.84,
      "high_50d": 202.19,
      "high_52w": 202.19,
      "diff_pct": 0.0,
      "recent_high_dates": [
        "2026-03-26"
      ]
    },
    {
      "ticker": "GPOR",
      "industry": "Oil & Gas E&P",
      "close": 216.42,
      "high_50d": 216.42,
      "high_52w": 222.49,
      "diff_pct": 2.8,
      "recent_high_dates": [
        "2026-03-25",
        "2026-03-26",
        "2026-03-27"
      ]
    },
    {
      "ticker": "GRNT",
      "industry": "Oil & Gas E&P",
      "close": 5.84,
      "high_50d": 5.9,
      "high_52w": 6.25,
      "diff_pct": 5.9,
      "recent_high_dates": [
        "2026-03-25",
        "2026-03-26"
      ]
    },
    {
      "ticker": "GTE",
      "industry": "Oil & Gas E&P",
      "close": 9.07,
      "high_50d": 9.07,
      "high_52w": 9.07,
      "diff_pct": 0.0,
      "recent_high_dates": [
        "2026-03-26",
        "2026-03-27"
      ]
    },
    {
      "ticker": "HPK",
      "industry": "Oil & Gas E&P",
      "close": 7.1,
      "high_50d": 7.1,
      "high_52w": 12.78,
      "diff_pct": 80.0,
      "recent_high_dates": [
        "2026-03-26",
        "2026-03-27"
      ]
    },
    {
      "ticker": "INR",
      "industry": "Oil & Gas E&P",
      "close": 19.23,
      "high_50d": 19.23,
      "high_52w": 19.56,
      "diff_pct": 1.7,
      "recent_high_dates": [
        "2026-03-27"
      ]
    },
    {
      "ticker": "KGEI",
      "industry": "Oil & Gas E&P",
      "close": 5.88,
      "high_50d": 5.88,
      "high_52w": 8.85,
      "diff_pct": 50.5,
      "recent_high_dates": [
        "2026-03-26",
        "2026-03-27"
      ]
    },
    {
      "ticker": "KRP",
      "industry": "Oil & Gas E&P",
      "close": 14.71,
      "high_50d": 14.71,
      "high_52w": 14.71,
      "diff_pct": 0.0,
      "recent_high_dates": [
        "2026-03-27"
      ]
    },
    {
      "ticker": "MGY",
      "industry": "Oil & Gas E&P",
      "close": 32.36,
      "high_50d": 32.36,
      "high_52w": 32.36,
      "diff_pct": 0.0,
      "recent_high_dates": [
        "2026-03-25",
        "2026-03-26",
        "2026-03-27"
      ]
    },
    {
      "ticker": "MNR",
      "industry": "Oil & Gas E&P",
      "close": 14.57,
      "high_50d": 14.57,
      "high_52w": 14.57,
      "diff_pct": 0.0,
      "recent_high_dates": [
        "2026-03-26",
        "2026-03-27"
      ]
    },
    {
      "ticker": "MTDR",
      "industry": "Oil & Gas E&P",
      "close": 65.45,
      "high_50d": 65.45,
      "high_52w": 65.45,
      "diff_pct": 0.0,
      "recent_high_dates": [
        "2026-03-25",
        "2026-03-26",
        "2026-03-27"
      ]
    },
    {
      "ticker": "MUR",
      "industry": "Oil & Gas E&P",
      "close": 42.12,
      "high_50d": 42.12,
      "high_52w": 42.12,
      "diff_pct": 0.0,
      "recent_high_dates": [
        "2026-03-25",
        "2026-03-26",
        "2026-03-27"
      ]
    },
    {
      "ticker": "NOG",
      "industry": "Oil & Gas E&P",
      "close": 30.82,
      "high_50d": 30.82,
      "high_52w": 30.82,
      "diff_pct": 0.0,
      "recent_high_dates": [
        "2026-03-25",
        "2026-03-26",
        "2026-03-27"
      ]
    },
    {
      "ticker": "OBE",
      "industry": "Oil & Gas E&P",
      "close": 9.24,
      "high_50d": 9.24,
      "high_52w": 9.24,
      "diff_pct": 0.0,
      "recent_high_dates": [
        "2026-03-25",
        "2026-03-27"
      ]
    },
    {
      "ticker": "OVV",
      "industry": "Oil & Gas E&P",
      "close": 62.08,
      "high_50d": 62.08,
      "high_52w": 62.08,
      "diff_pct": 0.0,
      "recent_high_dates": [
        "2026-03-25",
        "2026-03-26",
        "2026-03-27"
      ]
    },
    {
      "ticker": "OXY",
      "industry": "Oil & Gas E&P",
      "close": 65.32,
      "high_50d": 65.32,
      "high_52w": 65.32,
      "diff_pct": 0.0,
      "recent_high_dates": [
        "2026-03-25",
        "2026-03-26",
        "2026-03-27"
      ]
    },
    {
      "ticker": "PNRG",
      "industry": "Oil & Gas E&P",
      "close": 240.42,
      "high_50d": 240.42,
      "high_52w": 240.42,
      "diff_pct": 0.0,
      "recent_high_dates": [
        "2026-03-26",
        "2026-03-27"
      ]
    },
    {
      "ticker": "PR",
      "industry": "Oil & Gas E&P",
      "close": 21.65,
      "high_50d": 21.65,
      "high_52w": 21.65,
      "diff_pct": 0.0,
      "recent_high_dates": [
        "2026-03-25",
        "2026-03-26",
        "2026-03-27"
      ]
    },
    {
      "ticker": "REI",
      "industry": "Oil & Gas E&P",
      "close": 1.58,
      "high_50d": 1.59,
      "high_52w": 1.59,
      "diff_pct": 0.0,
      "recent_high_dates": [
        "2026-03-25",
        "2026-03-26"
      ]
    },
    {
      "ticker": "RRC",
      "industry": "Oil & Gas E&P",
      "close": 47.65,
      "high_50d": 47.65,
      "high_52w": 47.65,
      "diff_pct": 0.0,
      "recent_high_dates": [
        "2026-03-25",
        "2026-03-26",
        "2026-03-27"
      ]
    },
    {
      "ticker": "SM",
      "industry": "Oil & Gas E&P",
      "close": 32.72,
      "high_50d": 32.72,
      "high_52w": 32.72,
      "diff_pct": 0.0,
      "recent_high_dates": [
        "2026-03-25",
        "2026-03-26",
        "2026-03-27"
      ]
    },
    {
      "ticker": "TALO",
      "industry": "Oil & Gas E&P",
      "close": 16.57,
      "high_50d": 16.57,
      "high_52w": 16.57,
      "diff_pct": 0.0,
      "recent_high_dates": [
        "2026-03-25",
        "2026-03-26",
        "2026-03-27"
      ]
    },
    {
      "ticker": "TBN",
      "industry": "Oil & Gas E&P",
      "close": 43.4,
      "high_50d": 43.4,
      "high_52w": 43.4,
      "diff_pct": 0.0,
      "recent_high_dates": [
        "2026-03-26",
        "2026-03-27"
      ]
    },
    {
      "ticker": "TXO",
      "industry": "Oil & Gas E&P",
      "close": 13.14,
      "high_50d": 13.14,
      "high_52w": 17.1,
      "diff_pct": 30.1,
      "recent_high_dates": [
        "2026-03-26",
        "2026-03-27"
      ]
    },
    {
      "ticker": "VIST",
      "industry": "Oil & Gas E&P",
      "close": 74.21,
      "high_50d": 74.21,
      "high_52w": 74.21,
      "diff_pct": 0.0,
      "recent_high_dates": [
        "2026-03-27"
      ]
    },
    {
      "ticker": "WDS",
      "industry": "Oil & Gas E&P",
      "close": 24.78,
      "high_50d": 24.78,
      "high_52w": 24.78,
      "diff_pct": 0.0,
      "recent_high_dates": [
        "2026-03-27"
      ]
    },
    {
      "ticker": "AESI",
      "industry": "Oil & Gas Equipment & Services",
      "close": 13.22,
      "high_50d": 14.0,
      "high_52w": 17.68,
      "diff_pct": 26.3,
      "recent_high_dates": [
        "2026-03-26"
      ]
    },
    {
      "ticker": "FTI",
      "industry": "Oil & Gas Equipment & Services",
      "close": 71.19,
      "high_50d": 71.19,
      "high_52w": 71.19,
      "diff_pct": 0.0,
      "recent_high_dates": [
        "2026-03-25",
        "2026-03-27"
      ]
    },
    {
      "ticker": "HAL",
      "industry": "Oil & Gas Equipment & Services",
      "close": 40.42,
      "high_50d": 40.42,
      "high_52w": 40.42,
      "diff_pct": 0.0,
      "recent_high_dates": [
        "2026-03-25",
        "2026-03-26",
        "2026-03-27"
      ]
    },
    {
      "ticker": "KGS",
      "industry": "Oil & Gas Equipment & Services",
      "close": 58.47,
      "high_50d": 59.12,
      "high_52w": 59.12,
      "diff_pct": 0.0,
      "recent_high_dates": [
        "2026-03-25"
      ]
    },
    {
      "ticker": "NCSM",
      "industry": "Oil & Gas Equipment & Services",
      "close": 73.0,
      "high_50d": 73.0,
      "high_52w": 73.0,
      "diff_pct": 0.0,
      "recent_high_dates": [
        "2026-03-25",
        "2026-03-27"
      ]
    },
    {
      "ticker": "NEXT",
      "industry": "Oil & Gas Equipment & Services",
      "close": 8.13,
      "high_50d": 8.15,
      "high_52w": 12.0,
      "diff_pct": 47.2,
      "recent_high_dates": [
        "2026-03-25",
        "2026-03-26"
      ]
    },
    {
      "ticker": "NGS",
      "industry": "Oil & Gas Equipment & Services",
      "close": 39.81,
      "high_50d": 39.82,
      "high_52w": 39.82,
      "diff_pct": 0.0,
      "recent_high_dates": [
        "2026-03-25"
      ]
    },
    {
      "ticker": "NPKI",
      "industry": "Oil & Gas Equipment & Services",
      "close": 14.61,
      "high_50d": 14.93,
      "high_52w": 14.93,
      "diff_pct": 0.0,
      "recent_high_dates": [
        "2026-03-25"
      ]
    },
    {
      "ticker": "RES",
      "industry": "Oil & Gas Equipment & Services",
      "close": 7.32,
      "high_50d": 7.32,
      "high_52w": 7.32,
      "diff_pct": 0.0,
      "recent_high_dates": [
        "2026-03-26",
        "2026-03-27"
      ]
    },
    {
      "ticker": "SLB",
      "industry": "Oil & Gas Equipment & Services",
      "close": 53.5,
      "high_50d": 53.5,
      "high_52w": 53.5,
      "diff_pct": 0.0,
      "recent_high_dates": [
        "2026-03-25",
        "2026-03-26",
        "2026-03-27"
      ]
    },
    {
      "ticker": "SND",
      "industry": "Oil & Gas Equipment & Services",
      "close": 5.47,
      "high_50d": 5.47,
      "high_52w": 5.47,
      "diff_pct": 0.0,
      "recent_high_dates": [
        "2026-03-27"
      ]
    },
    {
      "ticker": "TS",
      "industry": "Oil & Gas Equipment & Services",
      "close": 58.29,
      "high_50d": 58.33,
      "high_52w": 58.33,
      "diff_pct": 0.0,
      "recent_high_dates": [
        "2026-03-26"
      ]
    },
    {
      "ticker": "VAL",
      "industry": "Oil & Gas Equipment & Services",
      "close": 102.24,
      "high_50d": 102.24,
      "high_52w": 102.24,
      "diff_pct": 0.0,
      "recent_high_dates": [
        "2026-03-25",
        "2026-03-26",
        "2026-03-27"
      ]
    },
    {
      "ticker": "WTTR",
      "industry": "Oil & Gas Equipment & Services",
      "close": 15.61,
      "high_50d": 15.61,
      "high_52w": 15.61,
      "diff_pct": 0.0,
      "recent_high_dates": [
        "2026-03-25",
        "2026-03-26",
        "2026-03-27"
      ]
    },
    {
      "ticker": "BP",
      "industry": "Oil & Gas Integrated",
      "close": 46.68,
      "high_50d": 46.68,
      "high_52w": 46.68,
      "diff_pct": 0.0,
      "recent_high_dates": [
        "2026-03-26",
        "2026-03-27"
      ]
    },
    {
      "ticker": "CVE",
      "industry": "Oil & Gas Integrated",
      "close": 26.82,
      "high_50d": 26.82,
      "high_52w": 26.82,
      "diff_pct": 0.0,
      "recent_high_dates": [
        "2026-03-25",
        "2026-03-26",
        "2026-03-27"
      ]
    },
    {
      "ticker": "CVX",
      "industry": "Oil & Gas Integrated",
      "close": 211.15,
      "high_50d": 211.15,
      "high_52w": 211.15,
      "diff_pct": 0.0,
      "recent_high_dates": [
        "2026-03-26",
        "2026-03-27"
      ]
    },
    {
      "ticker": "DEC",
      "industry": "Oil & Gas Integrated",
      "close": 18.16,
      "high_50d": 18.16,
      "high_52w": 18.16,
      "diff_pct": 0.0,
      "recent_high_dates": [
        "2026-03-25",
        "2026-03-26",
        "2026-03-27"
      ]
    },
    {
      "ticker": "E",
      "industry": "Oil & Gas Integrated",
      "close": 55.22,
      "high_50d": 55.22,
      "high_52w": 55.22,
      "diff_pct": 0.0,
      "recent_high_dates": [
        "2026-03-26",
        "2026-03-27"
      ]
    },
    {
      "ticker": "EC",
      "industry": "Oil & Gas Integrated",
      "close": 15.01,
      "high_50d": 15.01,
      "high_52w": 15.01,
      "diff_pct": 0.0,
      "recent_high_dates": [
        "2026-03-25",
        "2026-03-27"
      ]
    },
    {
      "ticker": "IMO",
      "industry": "Oil & Gas Integrated",
      "close": 130.76,
      "high_50d": 130.76,
      "high_52w": 130.76,
      "diff_pct": 0.0,
      "recent_high_dates": [
        "2026-03-25",
        "2026-03-27"
      ]
    },
    {
      "ticker": "PBR",
      "industry": "Oil & Gas Integrated",
      "close": 20.77,
      "high_50d": 20.77,
      "high_52w": 20.77,
      "diff_pct": 0.0,
      "recent_high_dates": [
        "2026-03-25",
        "2026-03-26",
        "2026-03-27"
      ]
    },
    {
      "ticker": "PBR-A",
      "industry": "Oil & Gas Integrated",
      "close": 18.8,
      "high_50d": 18.8,
      "high_52w": 18.8,
      "diff_pct": 0.0,
      "recent_high_dates": [
        "2026-03-25",
        "2026-03-26",
        "2026-03-27"
      ]
    },
    {
      "ticker": "SU",
      "industry": "Oil & Gas Integrated",
      "close": 66.66,
      "high_50d": 66.66,
      "high_52w": 66.66,
      "diff_pct": 0.0,
      "recent_high_dates": [
        "2026-03-25",
        "2026-03-26",
        "2026-03-27"
      ]
    },
    {
      "ticker": "TGS",
      "industry": "Oil & Gas Integrated",
      "close": 34.37,
      "high_50d": 34.37,
      "high_52w": 34.37,
      "diff_pct": 0.0,
      "recent_high_dates": [
        "2026-03-27"
      ]
    },
    {
      "ticker": "XOM",
      "industry": "Oil & Gas Integrated",
      "close": 170.99,
      "high_50d": 170.99,
      "high_52w": 170.99,
      "diff_pct": 0.0,
      "recent_high_dates": [
        "2026-03-26",
        "2026-03-27"
      ]
    },
    {
      "ticker": "YPF",
      "industry": "Oil & Gas Integrated",
      "close": 45.17,
      "high_50d": 45.17,
      "high_52w": 45.17,
      "diff_pct": 0.0,
      "recent_high_dates": [
        "2026-03-25",
        "2026-03-26",
        "2026-03-27"
      ]
    },
    {
      "ticker": "AM",
      "industry": "Oil & Gas Midstream",
      "close": 23.19,
      "high_50d": 23.6,
      "high_52w": 23.6,
      "diff_pct": 0.0,
      "recent_high_dates": [
        "2026-03-25"
      ]
    },
    {
      "ticker": "ENB",
      "industry": "Oil & Gas Midstream",
      "close": 54.58,
      "high_50d": 54.58,
      "high_52w": 54.58,
      "diff_pct": 0.0,
      "recent_high_dates": [
        "2026-03-27"
      ]
    },
    {
      "ticker": "EPD",
      "industry": "Oil & Gas Midstream",
      "close": 39.28,
      "high_50d": 39.28,
      "high_52w": 39.28,
      "diff_pct": 0.0,
      "recent_high_dates": [
        "2026-03-25",
        "2026-03-26",
        "2026-03-27"
      ]
    },
    {
      "ticker": "ET",
      "industry": "Oil & Gas Midstream",
      "close": 19.67,
      "high_50d": 19.67,
      "high_52w": 19.67,
      "diff_pct": 0.0,
      "recent_high_dates": [
        "2026-03-26",
        "2026-03-27"
      ]
    },
    {
      "ticker": "GLNG",
      "industry": "Oil & Gas Midstream",
      "close": 55.03,
      "high_50d": 55.03,
      "high_52w": 55.03,
      "diff_pct": 0.0,
      "recent_high_dates": [
        "2026-03-27"
      ]
    },
    {
      "ticker": "KMI",
      "industry": "Oil & Gas Midstream",
      "close": 34.03,
      "high_50d": 34.07,
      "high_52w": 34.07,
      "diff_pct": 0.0,
      "recent_high_dates": [
        "2026-03-25",
        "2026-03-26"
      ]
    },
    {
      "ticker": "KNTK",
      "industry": "Oil & Gas Midstream",
      "close": 48.58,
      "high_50d": 48.64,
      "high_52w": 49.89,
      "diff_pct": 2.6,
      "recent_high_dates": [
        "2026-03-25",
        "2026-03-26"
      ]
    },
    {
      "ticker": "LNG",
      "industry": "Oil & Gas Midstream",
      "close": 296.91,
      "high_50d": 296.91,
      "high_52w": 296.91,
      "diff_pct": 0.0,
      "recent_high_dates": [
        "2026-03-27"
      ]
    },
    {
      "ticker": "OKE",
      "industry": "Oil & Gas Midstream",
      "close": 93.96,
      "high_50d": 93.96,
      "high_52w": 95.07,
      "diff_pct": 1.2,
      "recent_high_dates": [
        "2026-03-25",
        "2026-03-26",
        "2026-03-27"
      ]
    },
    {
      "ticker": "PAA",
      "industry": "Oil & Gas Midstream",
      "close": 22.44,
      "high_50d": 22.52,
      "high_52w": 22.52,
      "diff_pct": 0.0,
      "recent_high_dates": [
        "2026-03-26"
      ]
    },
    {
      "ticker": "PAGP",
      "industry": "Oil & Gas Midstream",
      "close": 24.46,
      "high_50d": 24.46,
      "high_52w": 24.46,
      "diff_pct": 0.0,
      "recent_high_dates": [
        "2026-03-26",
        "2026-03-27"
      ]
    },
    {
      "ticker": "PBA",
      "industry": "Oil & Gas Midstream",
      "close": 45.77,
      "high_50d": 45.77,
      "high_52w": 45.77,
      "diff_pct": 0.0,
      "recent_high_dates": [
        "2026-03-25",
        "2026-03-26",
        "2026-03-27"
      ]
    },
    {
      "ticker": "SBR",
      "industry": "Oil & Gas Midstream",
      "close": 76.29,
      "high_50d": 76.29,
      "high_52w": 80.06,
      "diff_pct": 4.9,
      "recent_high_dates": [
        "2026-03-27"
      ]
    },
    {
      "ticker": "SOBO",
      "industry": "Oil & Gas Midstream",
      "close": 34.21,
      "high_50d": 34.21,
      "high_52w": 34.21,
      "diff_pct": 0.0,
      "recent_high_dates": [
        "2026-03-25",
        "2026-03-27"
      ]
    },
    {
      "ticker": "TRGP",
      "industry": "Oil & Gas Midstream",
      "close": 250.23,
      "high_50d": 250.5,
      "high_52w": 250.5,
      "diff_pct": 0.0,
      "recent_high_dates": [
        "2026-03-26"
      ]
    },
    {
      "ticker": "VG",
      "industry": "Oil & Gas Midstream",
      "close": 17.53,
      "high_50d": 17.53,
      "high_52w": 18.91,
      "diff_pct": 7.9,
      "recent_high_dates": [
        "2026-03-25",
        "2026-03-26",
        "2026-03-27"
      ]
    },
    {
      "ticker": "CVI",
      "industry": "Oil & Gas Refining & Marketing",
      "close": 34.83,
      "high_50d": 34.83,
      "high_52w": 39.4,
      "diff_pct": 13.1,
      "recent_high_dates": [
        "2026-03-26",
        "2026-03-27"
      ]
    },
    {
      "ticker": "DINO",
      "industry": "Oil & Gas Refining & Marketing",
      "close": 63.74,
      "high_50d": 63.74,
      "high_52w": 63.74,
      "diff_pct": 0.0,
      "recent_high_dates": [
        "2026-03-26",
        "2026-03-27"
      ]
    },
    {
      "ticker": "DK",
      "industry": "Oil & Gas Refining & Marketing",
      "close": 47.43,
      "high_50d": 47.43,
      "high_52w": 47.43,
      "diff_pct": 0.0,
      "recent_high_dates": [
        "2026-03-26",
        "2026-03-27"
      ]
    },
    {
      "ticker": "MPC",
      "industry": "Oil & Gas Refining & Marketing",
      "close": 251.91,
      "high_50d": 251.91,
      "high_52w": 251.91,
      "diff_pct": 0.0,
      "recent_high_dates": [
        "2026-03-26",
        "2026-03-27"
      ]
    },
    {
      "ticker": "PARR",
      "industry": "Oil & Gas Refining & Marketing",
      "close": 65.67,
      "high_50d": 65.67,
      "high_52w": 65.67,
      "diff_pct": 0.0,
      "recent_high_dates": [
        "2026-03-26",
        "2026-03-27"
      ]
    },
    {
      "ticker": "PBF",
      "industry": "Oil & Gas Refining & Marketing",
      "close": 51.23,
      "high_50d": 51.23,
      "high_52w": 51.23,
      "diff_pct": 0.0,
      "recent_high_dates": [
        "2026-03-26",
        "2026-03-27"
      ]
    },
    {
      "ticker": "PSX",
      "industry": "Oil & Gas Refining & Marketing",
      "close": 188.28,
      "high_50d": 188.28,
      "high_52w": 188.28,
      "diff_pct": 0.0,
      "recent_high_dates": [
        "2026-03-27"
      ]
    },
    {
      "ticker": "UGP",
      "industry": "Oil & Gas Refining & Marketing",
      "close": 5.37,
      "high_50d": 5.41,
      "high_52w": 5.41,
      "diff_pct": 0.0,
      "recent_high_dates": [
        "2026-03-25"
      ]
    },
    {
      "ticker": "VLO",
      "industry": "Oil & Gas Refining & Marketing",
      "close": 254.32,
      "high_50d": 254.32,
      "high_52w": 254.32,
      "diff_pct": 0.0,
      "recent_high_dates": [
        "2026-03-26",
        "2026-03-27"
      ]
    },
    {
      "ticker": "DAR",
      "industry": "Packaged Foods",
      "close": 59.28,
      "high_50d": 59.28,
      "high_52w": 59.28,
      "diff_pct": 0.0,
      "recent_high_dates": [
        "2026-03-25",
        "2026-03-26",
        "2026-03-27"
      ]
    },
    {
      "ticker": "SENEA",
      "industry": "Packaged Foods",
      "close": 151.78,
      "high_50d": 151.78,
      "high_52w": 151.78,
      "diff_pct": 0.0,
      "recent_high_dates": [
        "2026-03-26",
        "2026-03-27"
      ]
    },
    {
      "ticker": "SFD",
      "industry": "Packaged Foods",
      "close": 26.69,
      "high_50d": 26.69,
      "high_52w": 26.69,
      "diff_pct": 0.0,
      "recent_high_dates": [
        "2026-03-26",
        "2026-03-27"
      ]
    },
    {
      "ticker": "KRT",
      "industry": "Packaging & Containers",
      "close": 27.6,
      "high_50d": 28.39,
      "high_52w": 30.64,
      "diff_pct": 7.9,
      "recent_high_dates": [
        "2026-03-25"
      ]
    },
    {
      "ticker": "SEE",
      "industry": "Packaging & Containers",
      "close": 42.0,
      "high_50d": 42.04,
      "high_52w": 42.99,
      "diff_pct": 2.3,
      "recent_high_dates": [
        "2026-03-25"
      ]
    },
    {
      "ticker": "SCWO",
      "industry": "Pollution & Treatment Controls",
      "close": 2.96,
      "high_50d": 3.5,
      "high_52w": 7.0,
      "diff_pct": 100.0,
      "recent_high_dates": [
        "2026-03-25"
      ]
    },
    {
      "ticker": "NYT",
      "industry": "Publishing",
      "close": 82.79,
      "high_50d": 85.17,
      "high_52w": 85.17,
      "diff_pct": 0.0,
      "recent_high_dates": [
        "2026-03-25"
      ]
    },
    {
      "ticker": "SCHL",
      "industry": "Publishing",
      "close": 38.74,
      "high_50d": 39.09,
      "high_52w": 39.09,
      "diff_pct": 0.0,
      "recent_high_dates": [
        "2026-03-25"
      ]
    },
    {
      "ticker": "TDAY",
      "industry": "Publishing",
      "close": 6.79,
      "high_50d": 6.79,
      "high_52w": 6.79,
      "diff_pct": 0.0,
      "recent_high_dates": [
        "2026-03-25",
        "2026-03-27"
      ]
    },
    {
      "ticker": "WLY",
      "industry": "Publishing",
      "close": 37.62,
      "high_50d": 38.26,
      "high_52w": 43.9,
      "diff_pct": 14.7,
      "recent_high_dates": [
        "2026-03-26"
      ]
    },
    {
      "ticker": "NLOP",
      "industry": "REIT - Office",
      "close": 14.59,
      "high_50d": 14.81,
      "high_52w": 14.81,
      "diff_pct": 0.0,
      "recent_high_dates": [
        "2026-03-25",
        "2026-03-26"
      ]
    },
    {
      "ticker": "BHM",
      "industry": "REIT - Residential",
      "close": 11.8,
      "high_50d": 12.08,
      "high_52w": 14.31,
      "diff_pct": 18.5,
      "recent_high_dates": [
        "2026-03-25"
      ]
    },
    {
      "ticker": "VRE",
      "industry": "REIT - Residential",
      "close": 18.93,
      "high_50d": 18.94,
      "high_52w": 18.94,
      "diff_pct": 0.0,
      "recent_high_dates": [
        "2026-03-25",
        "2026-03-26"
      ]
    },
    {
      "ticker": "SELF",
      "industry": "REIT - Specialty",
      "close": 5.04,
      "high_50d": 5.16,
      "high_52w": 5.44,
      "diff_pct": 5.4,
      "recent_high_dates": [
        "2026-03-25"
      ]
    },
    {
      "ticker": "LPA",
      "industry": "Real Estate - Development",
      "close": 3.46,
      "high_50d": 3.52,
      "high_52w": 9.36,
      "diff_pct": 165.9,
      "recent_high_dates": [
        "2026-03-26"
      ]
    },
    {
      "ticker": "CHCI",
      "industry": "Real Estate Services",
      "close": 16.83,
      "high_50d": 16.83,
      "high_52w": 18.56,
      "diff_pct": 10.3,
      "recent_high_dates": [
        "2026-03-26",
        "2026-03-27"
      ]
    },
    {
      "ticker": "AL",
      "industry": "Rental & Leasing Services",
      "close": 64.8,
      "high_50d": 64.8,
      "high_52w": 64.8,
      "diff_pct": 0.0,
      "recent_high_dates": [
        "2026-03-27"
      ]
    },
    {
      "ticker": "CAR",
      "industry": "Rental & Leasing Services",
      "close": 148.45,
      "high_50d": 148.45,
      "high_52w": 207.55,
      "diff_pct": 39.8,
      "recent_high_dates": [
        "2026-03-26",
        "2026-03-27"
      ]
    },
    {
      "ticker": "TPH",
      "industry": "Residential Construction",
      "close": 46.69,
      "high_50d": 46.72,
      "high_52w": 46.72,
      "diff_pct": 0.0,
      "recent_high_dates": [
        "2026-03-25"
      ]
    },
    {
      "ticker": "CHSN",
      "industry": "Restaurants",
      "close": 2.78,
      "high_50d": 2.84,
      "high_52w": 44.0,
      "diff_pct": 1449.3,
      "recent_high_dates": [
        "2026-03-26"
      ]
    },
    {
      "ticker": "LOCO",
      "industry": "Restaurants",
      "close": 13.81,
      "high_50d": 14.33,
      "high_52w": 14.33,
      "diff_pct": 0.0,
      "recent_high_dates": [
        "2026-03-25"
      ]
    },
    {
      "ticker": "NDLS",
      "industry": "Restaurants",
      "close": 9.2,
      "high_50d": 9.43,
      "high_52w": 9.44,
      "diff_pct": 0.1,
      "recent_high_dates": [
        "2026-03-26"
      ]
    },
    {
      "ticker": "ESE",
      "industry": "Scientific & Technical Instruments",
      "close": 279.23,
      "high_50d": 288.77,
      "high_52w": 288.77,
      "diff_pct": 0.0,
      "recent_high_dates": [
        "2026-03-25"
      ]
    },
    {
      "ticker": "KSCP",
      "industry": "Security & Protection Services",
      "close": 4.81,
      "high_50d": 5.53,
      "high_52w": 10.09,
      "diff_pct": 82.5,
      "recent_high_dates": [
        "2026-03-25",
        "2026-03-26"
      ]
    },
    {
      "ticker": "ACLS",
      "industry": "Semiconductor Equipment & Materials",
      "close": 97.35,
      "high_50d": 100.85,
      "high_52w": 100.85,
      "diff_pct": 0.0,
      "recent_high_dates": [
        "2026-03-25"
      ]
    },
    {
      "ticker": "FORM",
      "industry": "Semiconductor Equipment & Materials",
      "close": 97.93,
      "high_50d": 108.07,
      "high_52w": 108.07,
      "diff_pct": 0.0,
      "recent_high_dates": [
        "2026-03-25"
      ]
    },
    {
      "ticker": "INTT",
      "industry": "Semiconductor Equipment & Materials",
      "close": 14.03,
      "high_50d": 15.1,
      "high_52w": 15.1,
      "diff_pct": 0.0,
      "recent_high_dates": [
        "2026-03-25"
      ]
    },
    {
      "ticker": "VECO",
      "industry": "Semiconductor Equipment & Materials",
      "close": 35.27,
      "high_50d": 36.96,
      "high_52w": 36.96,
      "diff_pct": 0.0,
      "recent_high_dates": [
        "2026-03-25"
      ]
    },
    {
      "ticker": "AIP",
      "industry": "Semiconductors",
      "close": 16.51,
      "high_50d": 17.99,
      "high_52w": 19.67,
      "diff_pct": 9.3,
      "recent_high_dates": [
        "2026-03-25"
      ]
    },
    {
      "ticker": "AOSL",
      "industry": "Semiconductors",
      "close": 22.05,
      "high_50d": 23.31,
      "high_52w": 31.95,
      "diff_pct": 37.1,
      "recent_high_dates": [
        "2026-03-25"
      ]
    },
    {
      "ticker": "ARM",
      "industry": "Semiconductors",
      "close": 144.13,
      "high_50d": 157.07,
      "high_52w": 178.62,
      "diff_pct": 13.7,
      "recent_high_dates": [
        "2026-03-25"
      ]
    },
    {
      "ticker": "CRUS",
      "industry": "Semiconductors",
      "close": 143.39,
      "high_50d": 148.69,
      "high_52w": 148.69,
      "diff_pct": 0.0,
      "recent_high_dates": [
        "2026-03-26"
      ]
    },
    {
      "ticker": "LASR",
      "industry": "Semiconductors",
      "close": 64.32,
      "high_50d": 71.75,
      "high_52w": 71.75,
      "diff_pct": 0.0,
      "recent_high_dates": [
        "2026-03-25"
      ]
    },
    {
      "ticker": "MRVL",
      "industry": "Semiconductors",
      "close": 94.88,
      "high_50d": 98.45,
      "high_52w": 100.13,
      "diff_pct": 1.7,
      "recent_high_dates": [
        "2026-03-25"
      ]
    },
    {
      "ticker": "POWI",
      "industry": "Semiconductors",
      "close": 49.5,
      "high_50d": 51.99,
      "high_52w": 58.64,
      "diff_pct": 12.8,
      "recent_high_dates": [
        "2026-03-25"
      ]
    },
    {
      "ticker": "QUIK",
      "industry": "Semiconductors",
      "close": 9.53,
      "high_50d": 9.97,
      "high_52w": 9.97,
      "diff_pct": 0.0,
      "recent_high_dates": [
        "2026-03-25"
      ]
    },
    {
      "ticker": "TSEM",
      "industry": "Semiconductors",
      "close": 171.92,
      "high_50d": 188.74,
      "high_52w": 188.74,
      "diff_pct": 0.0,
      "recent_high_dates": [
        "2026-03-25"
      ]
    },
    {
      "ticker": "ALCY",
      "industry": "Shell Companies",
      "close": 11.9,
      "high_50d": 11.9,
      "high_52w": 15.24,
      "diff_pct": 28.1,
      "recent_high_dates": [
        "2026-03-27"
      ]
    },
    {
      "ticker": "ALF",
      "industry": "Shell Companies",
      "close": 10.79,
      "high_50d": 10.8,
      "high_52w": 10.8,
      "diff_pct": 0.0,
      "recent_high_dates": [
        "2026-03-25",
        "2026-03-26"
      ]
    },
    {
      "ticker": "CAPN",
      "industry": "Shell Companies",
      "close": 10.93,
      "high_50d": 10.93,
      "high_52w": 10.93,
      "diff_pct": 0.0,
      "recent_high_dates": [
        "2026-03-25",
        "2026-03-27"
      ]
    },
    {
      "ticker": "CHAR",
      "industry": "Shell Companies",
      "close": 10.58,
      "high_50d": 10.58,
      "high_52w": 10.58,
      "diff_pct": 0.0,
      "recent_high_dates": [
        "2026-03-25",
        "2026-03-26",
        "2026-03-27"
      ]
    },
    {
      "ticker": "CUB",
      "industry": "Shell Companies",
      "close": 10.74,
      "high_50d": 10.75,
      "high_52w": 10.75,
      "diff_pct": 0.0,
      "recent_high_dates": [
        "2026-03-25",
        "2026-03-26"
      ]
    },
    {
      "ticker": "ETHM",
      "industry": "Shell Companies",
      "close": 10.47,
      "high_50d": 10.47,
      "high_52w": 11.99,
      "diff_pct": 14.5,
      "recent_high_dates": [
        "2026-03-26",
        "2026-03-27"
      ]
    },
    {
      "ticker": "EURK",
      "industry": "Shell Companies",
      "close": 11.3,
      "high_50d": 11.3,
      "high_52w": 11.3,
      "diff_pct": 0.0,
      "recent_high_dates": [
        "2026-03-26",
        "2026-03-27"
      ]
    },
    {
      "ticker": "FGMC",
      "industry": "Shell Companies",
      "close": 10.1,
      "high_50d": 10.11,
      "high_52w": 10.11,
      "diff_pct": 0.0,
      "recent_high_dates": [
        "2026-03-25",
        "2026-03-26"
      ]
    },
    {
      "ticker": "FSHP",
      "industry": "Shell Companies",
      "close": 10.93,
      "high_50d": 10.93,
      "high_52w": 10.93,
      "diff_pct": 0.0,
      "recent_high_dates": [
        "2026-03-25",
        "2026-03-26",
        "2026-03-27"
      ]
    },
    {
      "ticker": "FVN",
      "industry": "Shell Companies",
      "close": 10.72,
      "high_50d": 10.72,
      "high_52w": 10.72,
      "diff_pct": 0.0,
      "recent_high_dates": [
        "2026-03-25",
        "2026-03-26",
        "2026-03-27"
      ]
    },
    {
      "ticker": "GIG",
      "industry": "Shell Companies",
      "close": 10.64,
      "high_50d": 10.66,
      "high_52w": 11.72,
      "diff_pct": 9.9,
      "recent_high_dates": [
        "2026-03-25"
      ]
    },
    {
      "ticker": "GPAT",
      "industry": "Shell Companies",
      "close": 10.82,
      "high_50d": 10.83,
      "high_52w": 10.83,
      "diff_pct": 0.0,
      "recent_high_dates": [
        "2026-03-26"
      ]
    },
    {
      "ticker": "HYAC",
      "industry": "Shell Companies",
      "close": 11.5,
      "high_50d": 11.51,
      "high_52w": 11.51,
      "diff_pct": 0.0,
      "recent_high_dates": [
        "2026-03-25"
      ]
    },
    {
      "ticker": "JACS",
      "industry": "Shell Companies",
      "close": 10.59,
      "high_50d": 10.59,
      "high_52w": 10.59,
      "diff_pct": 0.0,
      "recent_high_dates": [
        "2026-03-27"
      ]
    },
    {
      "ticker": "KVAC",
      "industry": "Shell Companies",
      "close": 12.0,
      "high_50d": 12.0,
      "high_52w": 12.0,
      "diff_pct": 0.0,
      "recent_high_dates": [
        "2026-03-25",
        "2026-03-26",
        "2026-03-27"
      ]
    },
    {
      "ticker": "LPBB",
      "industry": "Shell Companies",
      "close": 10.6,
      "high_50d": 10.63,
      "high_52w": 10.63,
      "diff_pct": 0.0,
      "recent_high_dates": [
        "2026-03-25",
        "2026-03-26"
      ]
    },
    {
      "ticker": "MACI",
      "industry": "Shell Companies",
      "close": 10.77,
      "high_50d": 10.77,
      "high_52w": 10.77,
      "diff_pct": 0.0,
      "recent_high_dates": [
        "2026-03-25",
        "2026-03-27"
      ]
    },
    {
      "ticker": "MBAV",
      "industry": "Shell Companies",
      "close": 10.79,
      "high_50d": 10.79,
      "high_52w": 13.53,
      "diff_pct": 25.4,
      "recent_high_dates": [
        "2026-03-26",
        "2026-03-27"
      ]
    },
    {
      "ticker": "MLAC",
      "industry": "Shell Companies",
      "close": 10.53,
      "high_50d": 10.55,
      "high_52w": 10.55,
      "diff_pct": 0.0,
      "recent_high_dates": [
        "2026-03-25"
      ]
    },
    {
      "ticker": "OACC",
      "industry": "Shell Companies",
      "close": 10.58,
      "high_50d": 10.7,
      "high_52w": 10.7,
      "diff_pct": 0.0,
      "recent_high_dates": [
        "2026-03-25"
      ]
    },
    {
      "ticker": "PLMK",
      "industry": "Shell Companies",
      "close": 10.56,
      "high_50d": 10.59,
      "high_52w": 10.59,
      "diff_pct": 0.0,
      "recent_high_dates": [
        "2026-03-25"
      ]
    },
    {
      "ticker": "POLE",
      "industry": "Shell Companies",
      "close": 10.63,
      "high_50d": 10.65,
      "high_52w": 10.8,
      "diff_pct": 1.4,
      "recent_high_dates": [
        "2026-03-25"
      ]
    },
    {
      "ticker": "RANG",
      "industry": "Shell Companies",
      "close": 10.51,
      "high_50d": 10.52,
      "high_52w": 10.73,
      "diff_pct": 2.0,
      "recent_high_dates": [
        "2026-03-25"
      ]
    },
    {
      "ticker": "RFAI",
      "industry": "Shell Companies",
      "close": 10.9,
      "high_50d": 10.93,
      "high_52w": 10.99,
      "diff_pct": 0.5,
      "recent_high_dates": [
        "2026-03-26"
      ]
    },
    {
      "ticker": "TAVI",
      "industry": "Shell Companies",
      "close": 10.55,
      "high_50d": 10.55,
      "high_52w": 10.55,
      "diff_pct": 0.0,
      "recent_high_dates": [
        "2026-03-26",
        "2026-03-27"
      ]
    },
    {
      "ticker": "TDAC",
      "industry": "Shell Companies",
      "close": 10.58,
      "high_50d": 10.58,
      "high_52w": 10.58,
      "diff_pct": 0.0,
      "recent_high_dates": [
        "2026-03-25",
        "2026-03-26",
        "2026-03-27"
      ]
    },
    {
      "ticker": "VACH",
      "industry": "Shell Companies",
      "close": 12.9,
      "high_50d": 12.9,
      "high_52w": 12.9,
      "diff_pct": 0.0,
      "recent_high_dates": [
        "2026-03-27"
      ]
    },
    {
      "ticker": "VCIC",
      "industry": "Shell Companies",
      "close": 11.04,
      "high_50d": 11.28,
      "high_52w": 11.99,
      "diff_pct": 6.3,
      "recent_high_dates": [
        "2026-03-26"
      ]
    },
    {
      "ticker": "FSLY",
      "industry": "Software - Application",
      "close": 27.43,
      "high_50d": 29.79,
      "high_52w": 29.79,
      "diff_pct": 0.0,
      "recent_high_dates": [
        "2026-03-25"
      ]
    },
    {
      "ticker": "IBTA",
      "industry": "Software - Application",
      "close": 28.98,
      "high_50d": 29.41,
      "high_52w": 60.24,
      "diff_pct": 104.8,
      "recent_high_dates": [
        "2026-03-25",
        "2026-03-26"
      ]
    },
    {
      "ticker": "MTC",
      "industry": "Software - Application",
      "close": 6.23,
      "high_50d": 6.95,
      "high_52w": 6.95,
      "diff_pct": 0.0,
      "recent_high_dates": [
        "2026-03-26"
      ]
    },
    {
      "ticker": "ONTF",
      "industry": "Software - Application",
      "close": 8.1,
      "high_50d": 8.1,
      "high_52w": 8.1,
      "diff_pct": 0.0,
      "recent_high_dates": [
        "2026-03-25",
        "2026-03-26",
        "2026-03-27"
      ]
    },
    {
      "ticker": "SVCO",
      "industry": "Software - Application",
      "close": 6.9,
      "high_50d": 7.26,
      "high_52w": 7.26,
      "diff_pct": 0.0,
      "recent_high_dates": [
        "2026-03-26"
      ]
    },
    {
      "ticker": "YOU",
      "industry": "Software - Application",
      "close": 47.44,
      "high_50d": 54.48,
      "high_52w": 54.48,
      "diff_pct": 0.0,
      "recent_high_dates": [
        "2026-03-25"
      ]
    },
    {
      "ticker": "AKAM",
      "industry": "Software - Infrastructure",
      "close": 114.5,
      "high_50d": 119.15,
      "high_52w": 119.15,
      "diff_pct": 0.0,
      "recent_high_dates": [
        "2026-03-25"
      ]
    },
    {
      "ticker": "ATEN",
      "industry": "Software - Infrastructure",
      "close": 22.34,
      "high_50d": 23.26,
      "high_52w": 23.26,
      "diff_pct": 0.0,
      "recent_high_dates": [
        "2026-03-25"
      ]
    },
    {
      "ticker": "BAND",
      "industry": "Software - Infrastructure",
      "close": 16.86,
      "high_50d": 17.24,
      "high_52w": 18.29,
      "diff_pct": 6.1,
      "recent_high_dates": [
        "2026-03-25",
        "2026-03-26"
      ]
    },
    {
      "ticker": "DOCN",
      "industry": "Software - Infrastructure",
      "close": 81.42,
      "high_50d": 87.0,
      "high_52w": 87.0,
      "diff_pct": 0.0,
      "recent_high_dates": [
        "2026-03-25"
      ]
    },
    {
      "ticker": "FFIV",
      "industry": "Software - Infrastructure",
      "close": 281.98,
      "high_50d": 297.86,
      "high_52w": 343.17,
      "diff_pct": 15.2,
      "recent_high_dates": [
        "2026-03-25"
      ]
    },
    {
      "ticker": "NN",
      "industry": "Software - Infrastructure",
      "close": 17.87,
      "high_50d": 19.36,
      "high_52w": 19.36,
      "diff_pct": 0.0,
      "recent_high_dates": [
        "2026-03-25"
      ]
    },
    {
      "ticker": "NTCT",
      "industry": "Software - Infrastructure",
      "close": 31.86,
      "high_50d": 32.6,
      "high_52w": 32.6,
      "diff_pct": 0.0,
      "recent_high_dates": [
        "2026-03-25",
        "2026-03-26"
      ]
    },
    {
      "ticker": "OS",
      "industry": "Software - Infrastructure",
      "close": 23.98,
      "high_50d": 23.98,
      "high_52w": 29.17,
      "diff_pct": 21.6,
      "recent_high_dates": [
        "2026-03-25",
        "2026-03-26",
        "2026-03-27"
      ]
    },
    {
      "ticker": "PAYS",
      "industry": "Software - Infrastructure",
      "close": 5.62,
      "high_50d": 5.62,
      "high_52w": 8.56,
      "diff_pct": 52.3,
      "recent_high_dates": [
        "2026-03-25",
        "2026-03-26",
        "2026-03-27"
      ]
    },
    {
      "ticker": "NXT",
      "industry": "Solar",
      "close": 120.03,
      "high_50d": 130.42,
      "high_52w": 130.42,
      "diff_pct": 0.0,
      "recent_high_dates": [
        "2026-03-25"
      ]
    },
    {
      "ticker": "SEDG",
      "industry": "Solar",
      "close": 51.76,
      "high_50d": 51.76,
      "high_52w": 51.76,
      "diff_pct": 0.0,
      "recent_high_dates": [
        "2026-03-27"
      ]
    },
    {
      "ticker": "KODK",
      "industry": "Specialty Business Services",
      "close": 9.46,
      "high_50d": 9.46,
      "high_52w": 9.73,
      "diff_pct": 2.9,
      "recent_high_dates": [
        "2026-03-25",
        "2026-03-26",
        "2026-03-27"
      ]
    },
    {
      "ticker": "LICN",
      "industry": "Specialty Business Services",
      "close": 6.03,
      "high_50d": 6.03,
      "high_52w": 6.63,
      "diff_pct": 10.0,
      "recent_high_dates": [
        "2026-03-26",
        "2026-03-27"
      ]
    },
    {
      "ticker": "SPIR",
      "industry": "Specialty Business Services",
      "close": 12.36,
      "high_50d": 13.73,
      "high_52w": 14.05,
      "diff_pct": 2.3,
      "recent_high_dates": [
        "2026-03-25"
      ]
    },
    {
      "ticker": "WFCF",
      "industry": "Specialty Business Services",
      "close": 13.35,
      "high_50d": 13.75,
      "high_52w": 13.75,
      "diff_pct": 0.0,
      "recent_high_dates": [
        "2026-03-25",
        "2026-03-26"
      ]
    },
    {
      "ticker": "AMTX",
      "industry": "Specialty Chemicals",
      "close": 3.3,
      "high_50d": 3.3,
      "high_52w": 3.49,
      "diff_pct": 5.8,
      "recent_high_dates": [
        "2026-03-25",
        "2026-03-27"
      ]
    },
    {
      "ticker": "APD",
      "industry": "Specialty Chemicals",
      "close": 292.19,
      "high_50d": 293.17,
      "high_52w": 295.18,
      "diff_pct": 0.7,
      "recent_high_dates": [
        "2026-03-26"
      ]
    },
    {
      "ticker": "CC",
      "industry": "Specialty Chemicals",
      "close": 21.6,
      "high_50d": 21.6,
      "high_52w": 21.6,
      "diff_pct": 0.0,
      "recent_high_dates": [
        "2026-03-26",
        "2026-03-27"
      ]
    },
    {
      "ticker": "CLMT",
      "industry": "Specialty Chemicals",
      "close": 32.06,
      "high_50d": 32.06,
      "high_52w": 32.06,
      "diff_pct": 0.0,
      "recent_high_dates": [
        "2026-03-26",
        "2026-03-27"
      ]
    },
    {
      "ticker": "CMT",
      "industry": "Specialty Chemicals",
      "close": 21.96,
      "high_50d": 22.54,
      "high_52w": 22.54,
      "diff_pct": 0.0,
      "recent_high_dates": [
        "2026-03-26"
      ]
    },
    {
      "ticker": "ECVT",
      "industry": "Specialty Chemicals",
      "close": 12.84,
      "high_50d": 13.0,
      "high_52w": 13.0,
      "diff_pct": 0.0,
      "recent_high_dates": [
        "2026-03-25",
        "2026-03-26"
      ]
    },
    {
      "ticker": "GEVO",
      "industry": "Specialty Chemicals",
      "close": 2.52,
      "high_50d": 2.52,
      "high_52w": 2.64,
      "diff_pct": 4.8,
      "recent_high_dates": [
        "2026-03-25",
        "2026-03-27"
      ]
    },
    {
      "ticker": "KOP",
      "industry": "Specialty Chemicals",
      "close": 37.92,
      "high_50d": 38.77,
      "high_52w": 38.77,
      "diff_pct": 0.0,
      "recent_high_dates": [
        "2026-03-26"
      ]
    },
    {
      "ticker": "LWLG",
      "industry": "Specialty Chemicals",
      "close": 7.24,
      "high_50d": 8.59,
      "high_52w": 8.59,
      "diff_pct": 0.0,
      "recent_high_dates": [
        "2026-03-25"
      ]
    },
    {
      "ticker": "LYB",
      "industry": "Specialty Chemicals",
      "close": 80.45,
      "high_50d": 80.45,
      "high_52w": 80.45,
      "diff_pct": 0.0,
      "recent_high_dates": [
        "2026-03-25",
        "2026-03-26",
        "2026-03-27"
      ]
    },
    {
      "ticker": "SSL",
      "industry": "Specialty Chemicals",
      "close": 12.71,
      "high_50d": 12.89,
      "high_52w": 12.89,
      "diff_pct": 0.0,
      "recent_high_dates": [
        "2026-03-25"
      ]
    },
    {
      "ticker": "WLK",
      "industry": "Specialty Chemicals",
      "close": 113.29,
      "high_50d": 114.22,
      "high_52w": 114.22,
      "diff_pct": 0.0,
      "recent_high_dates": [
        "2026-03-25"
      ]
    },
    {
      "ticker": "GEV",
      "industry": "Specialty Industrial Machinery",
      "close": 853.16,
      "high_50d": 923.69,
      "high_52w": 923.69,
      "diff_pct": 0.0,
      "recent_high_dates": [
        "2026-03-25"
      ]
    },
    {
      "ticker": "CASY",
      "industry": "Specialty Retail",
      "close": 714.24,
      "high_50d": 714.24,
      "high_52w": 714.24,
      "diff_pct": 0.0,
      "recent_high_dates": [
        "2026-03-25",
        "2026-03-27"
      ]
    },
    {
      "ticker": "MUSA",
      "industry": "Specialty Retail",
      "close": 506.24,
      "high_50d": 506.24,
      "high_52w": 517.23,
      "diff_pct": 2.2,
      "recent_high_dates": [
        "2026-03-26",
        "2026-03-27"
      ]
    },
    {
      "ticker": "OLPX",
      "industry": "Specialty Retail",
      "close": 2.02,
      "high_50d": 2.02,
      "high_52w": 2.02,
      "diff_pct": 0.0,
      "recent_high_dates": [
        "2026-03-26",
        "2026-03-27"
      ]
    },
    {
      "ticker": "ATEX",
      "industry": "Telecom Services",
      "close": 38.24,
      "high_50d": 40.57,
      "high_52w": 40.57,
      "diff_pct": 0.0,
      "recent_high_dates": [
        "2026-03-25"
      ]
    },
    {
      "ticker": "IRDM",
      "industry": "Telecom Services",
      "close": 27.96,
      "high_50d": 29.68,
      "high_52w": 31.71,
      "diff_pct": 6.8,
      "recent_high_dates": [
        "2026-03-25"
      ]
    },
    {
      "ticker": "KORE",
      "industry": "Telecom Services",
      "close": 8.99,
      "high_50d": 9.0,
      "high_52w": 9.0,
      "diff_pct": 0.0,
      "recent_high_dates": [
        "2026-03-25",
        "2026-03-26"
      ]
    },
    {
      "ticker": "LILA",
      "industry": "Telecom Services",
      "close": 8.33,
      "high_50d": 8.42,
      "high_52w": 8.87,
      "diff_pct": 5.3,
      "recent_high_dates": [
        "2026-03-25"
      ]
    },
    {
      "ticker": "LILAK",
      "industry": "Telecom Services",
      "close": 8.44,
      "high_50d": 8.49,
      "high_52w": 8.94,
      "diff_pct": 5.3,
      "recent_high_dates": [
        "2026-03-25"
      ]
    },
    {
      "ticker": "T",
      "industry": "Telecom Services",
      "close": 29.1,
      "high_50d": 29.1,
      "high_52w": 29.1,
      "diff_pct": 0.0,
      "recent_high_dates": [
        "2026-03-27"
      ]
    },
    {
      "ticker": "TIGO",
      "industry": "Telecom Services",
      "close": 75.33,
      "high_50d": 76.95,
      "high_52w": 76.95,
      "diff_pct": 0.0,
      "recent_high_dates": [
        "2026-03-25"
      ]
    },
    {
      "ticker": "ARLP",
      "industry": "Thermal Coal",
      "close": 28.99,
      "high_50d": 28.99,
      "high_52w": 28.99,
      "diff_pct": 0.0,
      "recent_high_dates": [
        "2026-03-26",
        "2026-03-27"
      ]
    },
    {
      "ticker": "BTU",
      "industry": "Thermal Coal",
      "close": 39.5,
      "high_50d": 39.5,
      "high_52w": 39.5,
      "diff_pct": 0.0,
      "recent_high_dates": [
        "2026-03-27"
      ]
    },
    {
      "ticker": "CNR",
      "industry": "Thermal Coal",
      "close": 113.23,
      "high_50d": 113.23,
      "high_52w": 113.23,
      "diff_pct": 0.0,
      "recent_high_dates": [
        "2026-03-25",
        "2026-03-27"
      ]
    },
    {
      "ticker": "TOUR",
      "industry": "Travel Services",
      "close": 0.77,
      "high_50d": 0.77,
      "high_52w": 1.1,
      "diff_pct": 42.9,
      "recent_high_dates": [
        "2026-03-25",
        "2026-03-27"
      ]
    },
    {
      "ticker": "ULH",
      "industry": "Trucking",
      "close": 19.99,
      "high_50d": 21.23,
      "high_52w": 29.6,
      "diff_pct": 39.4,
      "recent_high_dates": [
        "2026-03-25",
        "2026-03-26"
      ]
    },
    {
      "ticker": "CIG",
      "industry": "Utilities - Diversified",
      "close": 2.35,
      "high_50d": 2.4,
      "high_52w": 2.4,
      "diff_pct": 0.0,
      "recent_high_dates": [
        "2026-03-25"
      ]
    },
    {
      "ticker": "SRE",
      "industry": "Utilities - Diversified",
      "close": 95.88,
      "high_50d": 95.88,
      "high_52w": 95.88,
      "diff_pct": 0.0,
      "recent_high_dates": [
        "2026-03-27"
      ]
    },
    {
      "ticker": "ETR",
      "industry": "Utilities - Regulated Electric",
      "close": 109.88,
      "high_50d": 109.88,
      "high_52w": 109.88,
      "diff_pct": 0.0,
      "recent_high_dates": [
        "2026-03-27"
      ]
    }
  ]
}